{"duration":1319,"records":[{"duration":351,"stepId":"io.quarkus.hibernate.orm.deployment.HibernateOrmProcessor#enhancerDomainObjects","started":"01:51:19.504","dependents":[397,401,396],"id":395,"thread":"build-62"},{"duration":213,"stepId":"io.quarkus.vertx.http.deployment.devmode.console.DevConsoleProcessor#setupDeploymentSideHandling","started":"01:51:20.024","dependents":[411,410,412],"id":409,"thread":"build-13"},{"duration":178,"stepId":"io.quarkus.deployment.console.ConsoleProcessor#setupConsole","started":"01:51:19.052","dependents":[247,299,240,239,238],"id":237,"thread":"build-47"},{"duration":163,"stepId":"io.quarkus.devui.deployment.BuildTimeContentProcessor#createBuildTimeConstJsTemplate","started":"01:51:19.691","dependents":[400,399],"id":394,"thread":"build-25"},{"duration":133,"stepId":"io.quarkus.devui.deployment.DevUIProcessor#getAllExtensions","started":"01:51:19.552","dependents":[389,390,391,388],"id":387,"thread":"build-18"},{"duration":129,"stepId":"io.quarkus.hibernate.orm.deployment.HibernateOrmProcessor#parsePersistenceXmlDescriptors","started":"01:51:19.052","dependents":[305,234],"id":233,"thread":"build-43"},{"duration":126,"stepId":"io.quarkus.deployment.steps.ClassTransformingBuildStep#handleClassTransformation","started":"01:51:19.859","dependents":[408],"id":401,"thread":"build-62"},{"duration":126,"stepId":"io.quarkus.narayana.jta.deployment.NarayanaJtaProcessor#build","started":"01:51:19.128","dependents":[415,334,414,248,322],"id":244,"thread":"build-20"},{"duration":122,"stepId":"io.quarkus.devui.deployment.BuildTimeContentProcessor#createIndexHtmlTemplate","started":"01:51:19.855","dependents":[400],"id":399,"thread":"build-40"},{"duration":118,"stepId":"io.quarkus.vertx.http.deployment.devmode.ArcDevProcessor#eventsEndpoint","started":"01:51:19.026","dependents":[415,409,393],"id":206,"thread":"build-18"},{"duration":118,"stepId":"io.quarkus.deployment.logging.LoggingResourceProcessor#logConsoleCommand","started":"01:51:19.050","dependents":[320],"id":230,"thread":"build-45"},{"duration":115,"stepId":"io.quarkus.vertx.core.deployment.VertxCoreProcessor#createVertxContextHandlers","started":"01:51:19.029","dependents":[222,415,218],"id":198,"thread":"build-23"},{"duration":112,"stepId":"io.quarkus.deployment.steps.ApplicationIndexBuildStep#build","started":"01:51:19.059","dependents":[342,334,241,232],"id":231,"thread":"build-54"},{"duration":111,"stepId":"io.quarkus.deployment.steps.ConfigGenerationBuildStep#generateConfigClass","started":"01:51:19.541","dependents":[414],"id":382,"thread":"build-40"},{"duration":109,"stepId":"io.quarkus.netty.deployment.NettyProcessor#eagerlyInitClass","started":"01:51:19.029","dependents":[415],"id":186,"thread":"build-29"},{"duration":108,"stepId":"io.quarkus.vertx.http.deployment.devmode.ArcDevProcessor#invocationsEndpoint","started":"01:51:19.036","dependents":[415,409,393],"id":204,"thread":"build-19"},{"duration":106,"stepId":"io.quarkus.devui.deployment.logstream.LogStreamProcessor#handler","started":"01:51:19.037","dependents":[415,298],"id":207,"thread":"build-33"},{"duration":102,"stepId":"io.quarkus.arc.deployment.ArcProcessor#generateResources","started":"01:51:19.542","dependents":[415,414,372,401],"id":371,"thread":"build-20"},{"duration":102,"stepId":"io.quarkus.vertx.core.deployment.VertxCoreProcessor#ioThreadDetector","started":"01:51:19.042","dependents":[415,212],"id":199,"thread":"build-9"},{"duration":101,"stepId":"io.quarkus.devui.deployment.build.BuildMetricsDevUIProcessor#create","started":"01:51:19.037","dependents":[415],"id":189,"thread":"build-25"},{"duration":100,"stepId":"io.quarkus.smallrye.context.deployment.SmallRyeContextPropagationProcessor#buildStatic","started":"01:51:19.057","dependents":[415],"id":223,"thread":"build-35"},{"duration":98,"stepId":"io.quarkus.datasource.deployment.devservices.DevUIDatasourceProcessor#devConsoleCleanDatabaseHandler","started":"01:51:19.046","dependents":[415,409,393],"id":200,"thread":"build-3"},{"duration":98,"stepId":"io.quarkus.deployment.dev.io.NioThreadPoolDevModeProcessor#setupTCCL","started":"01:51:19.040","dependents":[415],"id":188,"thread":"build-2"},{"duration":95,"stepId":"io.quarkus.deployment.steps.BootstrapConfigSetupBuildStep#setupBootstrapConfig","started":"01:51:19.029","dependents":[415,182],"id":181,"thread":"build-8"},{"duration":95,"stepId":"io.quarkus.vertx.http.deployment.devmode.console.DevConsoleProcessor#handler","started":"01:51:19.049","dependents":[415,298,393],"id":208,"thread":"build-6"},{"duration":94,"stepId":"io.quarkus.resteasy.deployment.ResteasyStandaloneBuildStep#addDefaultAuthFailureHandler","started":"01:51:19.057","dependents":[415,406],"id":215,"thread":"build-57"},{"duration":92,"stepId":"io.quarkus.mutiny.deployment.MutinyProcessor#buildTimeInit","started":"01:51:19.046","dependents":[415],"id":187,"thread":"build-39"},{"duration":90,"stepId":"io.quarkus.deployment.steps.MainClassBuildStep#build","started":"01:51:20.240","dependents":[],"id":415,"thread":"build-40"},{"duration":90,"stepId":"io.quarkus.vertx.deployment.VertxProcessor#currentContextFactory","started":"01:51:19.054","dependents":[415,371],"id":205,"thread":"build-52"},{"duration":89,"stepId":"io.quarkus.deployment.steps.PreloadClassesBuildStep#preInit","started":"01:51:19.049","dependents":[415],"id":190,"thread":"build-22"},{"duration":89,"stepId":"io.quarkus.deployment.logging.LoggingResourceProcessor#registerMetrics","started":"01:51:19.053","dependents":[415,298],"id":196,"thread":"build-49"},{"duration":88,"stepId":"io.quarkus.vertx.core.deployment.VertxCoreProcessor#createVertxThreadFactory","started":"01:51:19.056","dependents":[415,218],"id":203,"thread":"build-53"},{"duration":87,"stepId":"io.quarkus.vertx.http.deployment.devmode.tests.TestsProcessor#setupTestRoutes","started":"01:51:19.072","dependents":[405,415,409,240,403],"id":224,"thread":"build-56"},{"duration":82,"stepId":"io.quarkus.deployment.steps.ConfigGenerationBuildStep#buildTimeRunTimeConfig","started":"01:51:19.049","dependents":[382,414],"id":183,"thread":"build-13"},{"duration":80,"stepId":"io.quarkus.deployment.logging.LoggingResourceProcessor#setupLoggingStaticInit","started":"01:51:19.058","dependents":[415],"id":185,"thread":"build-51"},{"duration":80,"stepId":"io.quarkus.deployment.index.ApplicationArchiveBuildStep#build","started":"01:51:19.172","dependents":[379,278,246,294,401,396,305,245,322,247,243,250,357,282,242],"id":241,"thread":"build-45"},{"duration":77,"stepId":"io.quarkus.arc.deployment.devconsole.ArcDevConsoleProcessor#exposeArcContainer","started":"01:51:19.061","dependents":[415,411],"id":191,"thread":"build-64"},{"duration":77,"stepId":"io.quarkus.resteasy.deployment.ResteasyBuiltinsProcessor#setupExceptionMapper","started":"01:51:19.069","dependents":[415,329],"id":211,"thread":"build-15"},{"duration":75,"stepId":"io.quarkus.deployment.steps.ConfigBuildSteps#generateConfigSources","started":"01:51:19.049","dependents":[],"id":179,"thread":"build-42"},{"duration":73,"stepId":"io.quarkus.vertx.http.deployment.VertxHttpProcessor#bodyHandler","started":"01:51:19.128","dependents":[415,406,393],"id":235,"thread":"build-28"},{"duration":71,"stepId":"io.quarkus.resteasy.deployment.ResteasyBuiltinsProcessor#addReactiveRoutesExceptionMapper","started":"01:51:19.069","dependents":[415],"id":194,"thread":"build-63"},{"duration":71,"stepId":"io.quarkus.deployment.console.ConsoleProcessor#quitCommand","started":"01:51:19.042","dependents":[320],"id":177,"thread":"build-27"},{"duration":69,"stepId":"io.quarkus.arc.deployment.ArcProcessor#registerBeans","started":"01:51:19.428","dependents":[342,344,346,338,343,350,352,345,347,341,339,340,349],"id":337,"thread":"build-31"},{"duration":69,"stepId":"io.quarkus.arc.deployment.ArcProcessor#buildCompatibleExtensions","started":"01:51:19.038","dependents":[334,322],"id":175,"thread":"build-34"},{"duration":69,"stepId":"io.quarkus.hibernate.orm.deployment.HibernateOrmProcessor#pregenProxies","started":"01:51:19.985","dependents":[415],"id":408,"thread":"build-65"},{"duration":65,"stepId":"io.quarkus.vertx.http.deployment.ManagementInterfaceSecurityProcessor#setupAuthenticationMechanisms","started":"01:51:19.084","dependents":[415,334,406,371,322],"id":214,"thread":"build-46"},{"duration":65,"stepId":"io.quarkus.deployment.console.ConsoleProcessor#helpCommand","started":"01:51:19.048","dependents":[320],"id":178,"thread":"build-24"},{"duration":62,"stepId":"io.quarkus.deployment.steps.ConfigGenerationBuildStep#setupConfigOverride","started":"01:51:19.061","dependents":[],"id":180,"thread":"build-59"},{"duration":59,"stepId":"io.quarkus.vertx.deployment.VertxProcessor#unremovableBeans","started":"01:51:19.023","dependents":[359,354],"id":150,"thread":"build-14"},{"duration":58,"stepId":"io.quarkus.datasource.deployment.DataSourcesExcludedFromHealthChecksProcessor#produceBean","started":"01:51:19.084","dependents":[415,350,347,349],"id":195,"thread":"build-62"},{"duration":58,"stepId":"io.quarkus.hibernate.orm.deployment.HibernateOrmProcessor#defineJpaEntities","started":"01:51:19.265","dependents":[315,414,301,395,311,302,313,408,305,308,377],"id":300,"thread":"build-31"},{"duration":56,"stepId":"io.quarkus.vertx.http.deployment.VertxHttpProcessor#logging","started":"01:51:19.030","dependents":[165],"id":164,"thread":"build-30"},{"duration":52,"stepId":"io.quarkus.deployment.steps.ConfigDescriptionBuildStep#createConfigDescriptions","started":"01:51:19.051","dependents":[409,321,319],"id":174,"thread":"build-5"},{"duration":50,"stepId":"io.quarkus.vertx.http.deployment.webjar.WebJarProcessor#processWebJarDevMode","started":"01:51:19.686","dependents":[415,391,392,393],"id":390,"thread":"build-20"},{"duration":49,"stepId":"io.quarkus.vertx.deployment.VertxProcessor#autoAddScope","started":"01:51:19.036","dependents":[328],"id":163,"thread":"build-32"},{"duration":49,"stepId":"io.quarkus.deployment.logging.LoggingResourceProcessor#setupLoggingRuntimeInit","started":"01:51:19.265","dependents":[415,409,414,299,407,393],"id":298,"thread":"build-18"},{"duration":49,"stepId":"io.quarkus.hibernate.orm.deployment.HibernateOrmCdiProcessor#registerAnnotations","started":"01:51:19.052","dependents":[283,284,334,322],"id":171,"thread":"build-48"},{"duration":48,"stepId":"io.quarkus.netty.deployment.NettyProcessor#setNettyMachineId","started":"01:51:19.025","dependents":[415],"id":140,"thread":"build-17"},{"duration":48,"stepId":"io.quarkiverse.caffeine.deployment.devui.CaffeineDevUIProcessor#createCard","started":"01:51:19.029","dependents":[370,387],"id":142,"thread":"build-10"},{"duration":47,"stepId":"io.quarkus.arc.deployment.ArcProcessor#quarkusMain","started":"01:51:19.055","dependents":[283,284,334,322],"id":170,"thread":"build-11"},{"duration":46,"stepId":"io.quarkus.undertow.deployment.WebXmlParsingBuildStep#createWebMetadata","started":"01:51:19.252","dependents":[334,295,385,296,322],"id":294,"thread":"build-28"},{"duration":45,"stepId":"io.quarkus.vertx.http.deployment.VertxHttpProcessor#filterMultipleVertxInstancesWarning","started":"01:51:19.023","dependents":[298,139],"id":129,"thread":"build-15"},{"duration":44,"stepId":"io.quarkus.devui.deployment.DevUIProcessor#registerDevUiHandlers","started":"01:51:19.980","dependents":[405,415,409,403],"id":402,"thread":"build-40"},{"duration":42,"stepId":"io.quarkus.hibernate.orm.deployment.dev.HibernateOrmDevUIProcessor#additionalBeans","started":"01:51:19.060","dependents":[334,322],"id":172,"thread":"build-20"},{"duration":42,"stepId":"io.quarkus.deployment.ide.IdeProcessor#detectRunningIdeProcesses","started":"01:51:19.025","dependents":[144],"id":127,"thread":"build-16"},{"duration":42,"stepId":"io.quarkus.devui.deployment.build.BuildMetricsDevUIProcessor#additionalBeans","started":"01:51:19.060","dependents":[334,322],"id":173,"thread":"build-31"},{"duration":41,"stepId":"io.quarkus.arc.deployment.CommandLineArgumentsProcessor#commandLineArgs","started":"01:51:19.039","dependents":[334,350,347,349,322],"id":146,"thread":"build-12"},{"duration":39,"stepId":"io.quarkus.agroal.deployment.AgroalProcessor#generateDataSourceSupportBean","started":"01:51:19.112","dependents":[415,359,334,350,347,354,349,322],"id":216,"thread":"build-31"},{"duration":38,"stepId":"io.quarkus.deployment.steps.BannerProcessor#recordBanner","started":"01:51:19.128","dependents":[415,298],"id":229,"thread":"build-27"},{"duration":37,"stepId":"io.quarkus.vertx.http.deployment.VertxHttpProcessor#preinitializeRouter","started":"01:51:19.164","dependents":[405,415,350,347,349],"id":236,"thread":"build-24"},{"duration":35,"stepId":"io.quarkus.resteasy.common.deployment.ResteasyCommonProcessor#setupProviders","started":"01:51:19.373","dependents":[359,414,330,354],"id":329,"thread":"build-31"},{"duration":35,"stepId":"io.quarkus.arc.deployment.LoggingBeanSupportProcessor#discoveredComponents","started":"01:51:19.047","dependents":[283,284,334,322],"id":148,"thread":"build-40"},{"duration":34,"stepId":"io.quarkus.undertow.deployment.UndertowBuildStep#servletContextBean","started":"01:51:19.265","dependents":[415,350,347,349],"id":297,"thread":"build-17"},{"duration":33,"stepId":"io.quarkus.arc.deployment.ConfigBuildStep#registerConfigRootsAsBeans","started":"01:51:19.051","dependents":[350,347,349],"id":158,"thread":"build-44"},{"duration":33,"stepId":"io.quarkus.deployment.steps.NativeImageConfigBuildStep#build","started":"01:51:19.112","dependents":[415],"id":209,"thread":"build-5"},{"duration":32,"stepId":"io.quarkus.hibernate.orm.deployment.HibernateOrmCdiProcessor#generateJpaConfigBean","started":"01:51:19.128","dependents":[415,350,347,349],"id":225,"thread":"build-24"},{"duration":31,"stepId":"io.quarkus.devui.deployment.menu.ContinuousTestingProcessor#createJsonRPCService","started":"01:51:19.025","dependents":[292,159],"id":102,"thread":"build-21"},{"duration":31,"stepId":"io.quarkus.agroal.deployment.AgroalMetricsProcessor#registerMetrics","started":"01:51:19.112","dependents":[415],"id":197,"thread":"build-34"},{"duration":28,"stepId":"io.quarkus.vertx.http.deployment.devmode.console.DevConsoleProcessor#setupConsole","started":"01:51:19.072","dependents":[411,410,412],"id":169,"thread":"build-28"},{"duration":27,"stepId":"io.quarkus.agroal.deployment.AgroalProcessor#build","started":"01:51:19.084","dependents":[334,414,197,209,248,216,322],"id":176,"thread":"build-41"},{"duration":26,"stepId":"io.quarkus.vertx.http.deployment.devmode.console.DevConsoleProcessor#collectTemplates","started":"01:51:19.059","dependents":[409],"id":160,"thread":"build-50"},{"duration":25,"stepId":"io.quarkus.deployment.DockerStatusProcessor#IsDockerWorking","started":"01:51:19.057","dependents":[316,299],"id":151,"thread":"build-21"},{"duration":24,"stepId":"io.quarkus.deployment.steps.ConfigGenerationBuildStep#checkForBuildTimeConfigChange","started":"01:51:19.128","dependents":[415],"id":217,"thread":"build-48"},{"duration":24,"stepId":"io.quarkus.netty.deployment.NettyProcessor#cleanupUnsafeLog","started":"01:51:19.046","dependents":[298,139],"id":136,"thread":"build-28"},{"duration":24,"stepId":"io.quarkus.arc.deployment.ArcProcessor#validate","started":"01:51:19.514","dependents":[359,358,356,362,361,366,401,360,357,355,367,371],"id":354,"thread":"build-31"},{"duration":24,"stepId":"io.quarkus.resteasy.server.common.deployment.ResteasyServerCommonProcessor#beanDefiningAnnotations","started":"01:51:19.058","dependents":[283,284,334,322],"id":149,"thread":"build-36"},{"duration":23,"stepId":"io.quarkus.deployment.pkg.steps.FileSystemResourcesBuildStep#notNormalMode","started":"01:51:19.057","dependents":[],"id":145,"thread":"build-41"},{"duration":23,"stepId":"io.quarkus.arc.deployment.BeanArchiveProcessor#build","started":"01:51:19.349","dependents":[323,334,330,327,324,326,346,345,329,328],"id":322,"thread":"build-20"},{"duration":21,"stepId":"io.quarkus.deployment.steps.CapabilityAggregationStep#provideCapabilities","started":"01:51:19.059","dependents":[152],"id":147,"thread":"build-60"},{"duration":21,"stepId":"io.quarkus.deployment.dev.testing.TestTracingProcessor#testConsoleCommand","started":"01:51:19.265","dependents":[320],"id":293,"thread":"build-62"},{"duration":21,"stepId":"io.quarkus.vertx.http.deployment.HttpSecurityProcessor#initBasicAuth","started":"01:51:19.128","dependents":[415,350,347,349],"id":213,"thread":"build-41"},{"duration":21,"stepId":"io.quarkus.deployment.ide.IdeProcessor#detectIdeFiles","started":"01:51:19.029","dependents":[144],"id":76,"thread":"build-5"},{"duration":20,"stepId":"io.quarkus.hibernate.orm.deployment.dev.HibernateOrmDevConsoleProcessor#exposeInfo","started":"01:51:19.059","dependents":[411],"id":143,"thread":"build-26"},{"duration":19,"stepId":"io.quarkus.vertx.core.deployment.VertxCoreProcessor#build_9d6b7122fb368970c50c3a870d1f672392cd8afb","started":"01:51:19.029","dependents":[414,209],"id":66,"thread":"build-22"},{"duration":19,"stepId":"io.quarkus.hibernate.orm.deployment.dev.HibernateOrmDevUIProcessor#createJsonRPCService","started":"01:51:19.018","dependents":[292,159],"id":31,"thread":"build-3"},{"duration":18,"stepId":"io.quarkus.resteasy.deployment.ResteasyBuiltinsProcessor#vertxProviders","started":"01:51:19.035","dependents":[329],"id":94,"thread":"build-31"},{"duration":18,"stepId":"io.quarkus.vertx.http.deployment.VertxHttpProcessor#frameworkRoot","started":"01:51:19.053","dependents":[389,405,224,169,402,409,394,366,392,406,393,399,141],"id":138,"thread":"build-38"},{"duration":17,"stepId":"io.quarkus.devui.deployment.DevUIProcessor#findAllJsonRPCMethods","started":"01:51:19.264","dependents":[394,381],"id":292,"thread":"build-40"},{"duration":17,"stepId":"io.quarkus.hibernate.orm.deployment.HibernateOrmProcessor#setupPersistenceProvider","started":"01:51:19.129","dependents":[415,377,221],"id":210,"thread":"build-17"},{"duration":17,"stepId":"io.quarkus.devui.deployment.DevUIProcessor#additionalBean","started":"01:51:19.068","dependents":[334,250,322],"id":159,"thread":"build-16"},{"duration":17,"stepId":"io.quarkus.hibernate.orm.deployment.HibernateOrmProcessor#configurationDescriptorBuilding","started":"01:51:19.324","dependents":[307,415,315,314,306,311,309,313,408,308],"id":305,"thread":"build-40"},{"duration":16,"stepId":"io.quarkus.deployment.CollectionClassProcessor#setupCollectionClasses","started":"01:51:19.020","dependents":[414],"id":25,"thread":"build-12"},{"duration":16,"stepId":"io.quarkus.vertx.http.deployment.VertxHttpProcessor#cors","started":"01:51:19.128","dependents":[415,406],"id":201,"thread":"build-8"},{"duration":16,"stepId":"io.quarkus.vertx.core.deployment.VertxCoreProcessor#eventLoopCount","started":"01:51:19.128","dependents":[415,413],"id":202,"thread":"build-40"},{"duration":15,"stepId":"io.quarkus.deployment.steps.ConfigGenerationBuildStep#watchConfigFiles","started":"01:51:19.028","dependents":[315],"id":50,"thread":"build-28"},{"duration":15,"stepId":"io.quarkus.narayana.jta.deployment.NarayanaJtaProcessor#unremovableBean","started":"01:51:19.051","dependents":[359,354],"id":124,"thread":"build-7"},{"duration":14,"stepId":"io.quarkus.deployment.recording.substitutions.AdditionalSubstitutionsBuildStep#additionalSubstitutions","started":"01:51:19.056","dependents":[415],"id":137,"thread":"build-56"},{"duration":14,"stepId":"io.quarkus.jackson.deployment.JacksonProcessor#register","started":"01:51:19.264","dependents":[333,334,414,322],"id":290,"thread":"build-20"},{"duration":14,"stepId":"io.quarkus.undertow.deployment.UndertowBuildStep#integrateCdi","started":"01:51:19.264","dependents":[334,385,322],"id":288,"thread":"build-35"},{"duration":13,"stepId":"io.quarkus.vertx.http.deployment.devmode.console.DevConsoleProcessor#setupWebJar","started":"01:51:19.053","dependents":[390],"id":125,"thread":"build-37"},{"duration":13,"stepId":"io.quarkus.vertx.http.deployment.VertxHttpProcessor#httpRoot","started":"01:51:19.055","dependents":[211,379,404,194,385,331,406,169],"id":130,"thread":"build-4"},{"duration":12,"stepId":"io.quarkus.deployment.ide.IdeProcessor#effectiveIde","started":"01:51:19.068","dependents":[409,166,247,239],"id":144,"thread":"build-62"},{"duration":12,"stepId":"io.quarkus.vertx.http.deployment.HttpSecurityProcessor#builtins","started":"01:51:19.264","dependents":[415,334,414,291,322],"id":286,"thread":"build-5"},{"duration":12,"stepId":"io.quarkus.jackson.deployment.JacksonProcessor#generateCustomizer","started":"01:51:19.265","dependents":[322],"id":287,"thread":"build-49"},{"duration":12,"stepId":"io.quarkus.deployment.steps.MainClassBuildStep#mainClassBuildStep","started":"01:51:19.263","dependents":[],"id":278,"thread":"build-47"},{"duration":12,"stepId":"io.quarkus.arc.deployment.devconsole.ArcDevConsoleProcessor#collectBeanInfo","started":"01:51:19.538","dependents":[369,409,368,393],"id":367,"thread":"build-5"},{"duration":12,"stepId":"io.quarkus.deployment.steps.RegisterForReflectionBuildStep#build","started":"01:51:19.265","dependents":[333,414],"id":289,"thread":"build-3"},{"duration":12,"stepId":"io.quarkus.undertow.deployment.UndertowBuildStep#registerUndertowHandlersConf","started":"01:51:19.264","dependents":[315,385],"id":282,"thread":"build-56"},{"duration":11,"stepId":"io.quarkus.vertx.deployment.VertxProcessor#registerVerticleClasses","started":"01:51:19.264","dependents":[414],"id":280,"thread":"build-8"},{"duration":11,"stepId":"io.quarkus.vertx.http.deployment.ManagementInterfaceSecurityProcessor#initBasicAuth","started":"01:51:19.128","dependents":[415,350,347,349],"id":192,"thread":"build-11"},{"duration":11,"stepId":"io.quarkus.undertow.deployment.UndertowBuildStep#build_4009234264941eeaf116a30d10a9c668499fb4ee","started":"01:51:19.653","dependents":[415,386,414],"id":385,"thread":"build-25"},{"duration":11,"stepId":"io.quarkus.vertx.http.deployment.HttpSecurityProcessor#initFormAuth","started":"01:51:19.128","dependents":[405,415,409,350,347,403,349],"id":193,"thread":"build-42"},{"duration":11,"stepId":"io.quarkus.deployment.dev.testing.TestTracingProcessor#startTesting","started":"01:51:19.230","dependents":[298,411,410,412],"id":240,"thread":"build-24"},{"duration":11,"stepId":"io.quarkus.arc.deployment.StartupBuildSteps#unremovableBeans","started":"01:51:19.058","dependents":[359,354],"id":131,"thread":"build-58"},{"duration":11,"stepId":"io.quarkus.devui.deployment.menu.ConfigurationProcessor#createConfigurationPages","started":"01:51:19.346","dependents":[389],"id":321,"thread":"build-53"},{"duration":11,"stepId":"io.quarkus.deployment.dev.HotDeploymentWatchedFileBuildStep#setupWatchedFileHotDeployment","started":"01:51:19.341","dependents":[411,410,412],"id":315,"thread":"build-17"},{"duration":11,"stepId":"io.quarkus.jackson.deployment.JacksonProcessor#supportMixins","started":"01:51:19.264","dependents":[415,414,350,347,349],"id":281,"thread":"build-48"},{"duration":11,"stepId":"io.quarkus.arc.deployment.ArcProcessor#initialize","started":"01:51:19.417","dependents":[335,336,337,367],"id":334,"thread":"build-18"},{"duration":10,"stepId":"io.quarkus.arc.deployment.BuildTimeEnabledProcessor#unlessBuildProperty","started":"01:51:19.264","dependents":[330,275],"id":274,"thread":"build-27"},{"duration":10,"stepId":"io.quarkus.deployment.steps.CombinedIndexBuildStep#build","started":"01:51:19.252","dependents":[386,334,278,252,254,251,327,290,341,274,255,296,332,253,260,282,333,288,304,330,281,311,286,267,396,258,292,305,273,266,297,256,302,335,329,261,269,257,262,397,285,287,272,289,280,279,270,276,263,358,384,362,298,385,339,271,259,264,277,293],"id":250,"thread":"build-54"},{"duration":10,"stepId":"io.quarkus.jackson.deployment.JacksonProcessor#unremovable","started":"01:51:19.265","dependents":[359,354],"id":285,"thread":"build-53"},{"duration":10,"stepId":"io.quarkus.vertx.core.deployment.VertxCoreProcessor#build_9fb3ce360263cc99d07c9172ec2feeaa85afcc1a","started":"01:51:19.154","dependents":[405,415,411,413,410,412,378,384,350,348,347,228,236,406,349],"id":227,"thread":"build-41"},{"duration":10,"stepId":"io.quarkus.vertx.core.deployment.VertxCoreProcessor#doNotRemoveVertxOptionsCustomizers","started":"01:51:19.018","dependents":[359,354],"id":12,"thread":"build-2"},{"duration":10,"stepId":"io.quarkus.vertx.http.deployment.devmode.console.ConfigEditorProcessor#config","started":"01:51:19.346","dependents":[415,409,320,411,393],"id":319,"thread":"build-62"},{"duration":10,"stepId":"io.quarkus.netty.deployment.NettyProcessor#cleanupMacDNSInLog","started":"01:51:19.025","dependents":[298,139],"id":20,"thread":"build-19"},{"duration":10,"stepId":"io.quarkus.resteasy.common.deployment.ResteasyCommonProcessor#registerJsonContextResolvers","started":"01:51:19.265","dependents":[359,334,354,329,322],"id":279,"thread":"build-9"},{"duration":10,"stepId":"io.quarkus.vertx.http.deployment.devmode.tests.TestsProcessor#handleTestStatus","started":"01:51:19.059","dependents":[409,393],"id":135,"thread":"build-46"},{"duration":9,"stepId":"io.quarkus.arc.deployment.BuildTimeEnabledProcessor#ifBuildProperty","started":"01:51:19.265","dependents":[330,275],"id":273,"thread":"build-23"},{"duration":9,"stepId":"io.quarkus.vertx.core.deployment.VertxCoreProcessor#registerVerticleClasses","started":"01:51:19.265","dependents":[414],"id":277,"thread":"build-45"},{"duration":9,"stepId":"io.quarkus.resteasy.deployment.ResteasyBuiltinsProcessor#setUpSecurity","started":"01:51:19.084","dependents":[334,329,322],"id":168,"thread":"build-40"},{"duration":9,"stepId":"io.quarkus.vertx.http.deployment.devmode.tests.TestsProcessor#printfailures","started":"01:51:19.029","dependents":[409,393],"id":36,"thread":"build-4"},{"duration":9,"stepId":"io.quarkus.arc.deployment.devconsole.ArcDevConsoleProcessor#monitor","started":"01:51:19.267","dependents":[334,411,322],"id":284,"thread":"build-33"},{"duration":9,"stepId":"io.quarkus.deployment.ExtensionLoader#config","started":"01:51:19.036","dependents":[67,183,342,386,334,278,193,308,248,208,406,225,405,415,359,401,74,227,105,245,121,378,167,104,371,368,379,299,311,93,83,174,78,158,297,241,80,197,84,366,407,364,196,291,329,229,393,213,87,272,98,413,233,279,412,325,276,237,384,298,89,235,326,88,221,96,108,410,106,138,97,322,284,375,144,205,390,118,244,231,296,382,100,176,99,195,210,363,184,214,130,215,330,286,119,201,115,305,283,266,409,185,149,154,309,360,192,217,116,240,202,114,385,218,236],"id":56,"thread":"build-26"},{"duration":9,"stepId":"io.quarkus.jdbc.h2.deployment.JDBCH2Processor#devDbHandler","started":"01:51:19.037","dependents":[299],"id":57,"thread":"build-24"},{"duration":9,"stepId":"io.quarkus.vertx.http.deployment.devmode.BuildMetricsDevConsoleProcessor#collectMetrics","started":"01:51:19.042","dependents":[369],"id":85,"thread":"build-4"},{"duration":9,"stepId":"io.quarkus.deployment.steps.ConfigGenerationBuildStep#extensionMappings","started":"01:51:19.264","dependents":[359,414,362,360,341,339],"id":272,"thread":"build-19"},{"duration":9,"stepId":"io.quarkus.hibernate.orm.deployment.metrics.HibernateOrmMetricsProcessor#metrics","started":"01:51:19.146","dependents":[415],"id":221,"thread":"build-5"},{"duration":9,"stepId":"io.quarkus.devservices.deployment.DevServicesProcessor#config","started":"01:51:19.346","dependents":[317,320,318],"id":316,"thread":"build-31"},{"duration":9,"stepId":"io.quarkus.deployment.steps.ThreadPoolSetup#createExecutor","started":"01:51:19.145","dependents":[222,226,415,219,386,384,220,227,406],"id":218,"thread":"build-40"},{"duration":9,"stepId":"io.quarkus.deployment.logging.LoggingResourceProcessor#setupLogFilters","started":"01:51:19.026","dependents":[298,139],"id":19,"thread":"build-24"},{"duration":9,"stepId":"io.quarkus.vertx.http.deployment.devmode.tests.TestsProcessor#toggleLiveReloadEnabled","started":"01:51:19.060","dependents":[409,393],"id":133,"thread":"build-61"},{"duration":9,"stepId":"io.quarkus.arc.deployment.devui.ArcDevUIProcessor#registerMonitoringComponents","started":"01:51:19.267","dependents":[334,322],"id":283,"thread":"build-24"},{"duration":8,"stepId":"io.quarkus.vertx.http.deployment.devmode.tests.TestsProcessor#toggleTestRunner","started":"01:51:19.044","dependents":[409,393],"id":90,"thread":"build-38"},{"duration":8,"stepId":"io.quarkus.vertx.http.deployment.devmode.tests.TestsProcessor#runFailedTests","started":"01:51:19.030","dependents":[409,393],"id":33,"thread":"build-7"},{"duration":8,"stepId":"io.quarkus.deployment.logging.LoggingResourceProcessor#setUpDarkeningDefault","started":"01:51:19.060","dependents":[363],"id":126,"thread":"build-62"},{"duration":8,"stepId":"io.quarkus.smallrye.context.deployment.SmallRyeContextPropagationProcessor#build","started":"01:51:19.154","dependents":[415,350,347,349],"id":226,"thread":"build-31"},{"duration":8,"stepId":"io.quarkus.deployment.dev.testing.TestTracingProcessor#sharedStateListener","started":"01:51:19.036","dependents":[240],"id":51,"thread":"build-20"},{"duration":8,"stepId":"io.quarkus.resteasy.server.common.deployment.ResteasyLogFilterBuildStep#setupLogFilters","started":"01:51:19.027","dependents":[298,139],"id":21,"thread":"build-25"},{"duration":8,"stepId":"io.quarkus.vertx.http.deployment.devmode.tests.TestsProcessor#runAllTests","started":"01:51:19.029","dependents":[409,393],"id":32,"thread":"build-6"},{"duration":8,"stepId":"io.quarkus.deployment.logging.LoggingResourceProcessor#setupStackTraceFormatter","started":"01:51:19.252","dependents":[298],"id":247,"thread":"build-47"},{"duration":8,"stepId":"io.quarkus.arc.deployment.SyntheticBeansProcessor#initRegular","started":"01:51:19.501","dependents":[352],"id":350,"thread":"build-28"},{"duration":8,"stepId":"io.quarkus.vertx.http.deployment.HttpSecurityProcessor#initMtlsClientAuth","started":"01:51:19.128","dependents":[415,350,347,349],"id":184,"thread":"build-26"},{"duration":8,"stepId":"io.quarkus.config.yaml.deployment.ConfigYamlProcessor#yamlConfig","started":"01:51:19.039","dependents":[382],"id":58,"thread":"build-6"},{"duration":8,"stepId":"io.quarkus.undertow.deployment.UndertowStaticResourcesBuildStep#scanStaticResources","started":"01:51:19.252","dependents":[385],"id":246,"thread":"build-24"},{"duration":8,"stepId":"io.quarkus.devui.deployment.BuildTimeContentProcessor#gatherMvnpmJars","started":"01:51:19.061","dependents":[399,402],"id":134,"thread":"build-66"},{"duration":8,"stepId":"io.quarkus.arc.deployment.UnremovableAnnotationsProcessor#unremovableBeans","started":"01:51:19.061","dependents":[359,354],"id":132,"thread":"build-65"},{"duration":8,"stepId":"io.quarkus.devui.deployment.logstream.LogStreamProcessor#additionalBean","started":"01:51:19.020","dependents":[334,322],"id":13,"thread":"build-13"},{"duration":7,"stepId":"io.quarkus.hibernate.orm.deployment.HibernateOrmCdiProcessor#generateDataSourceBeans","started":"01:51:19.341","dependents":[415,334,350,347,349,322],"id":314,"thread":"build-18"},{"duration":7,"stepId":"io.quarkus.resteasy.server.common.deployment.ResteasyServerCommonProcessor#build","started":"01:51:19.408","dependents":[333,359,334,380,379,414,401,331,354],"id":330,"thread":"build-40"},{"duration":7,"stepId":"io.quarkus.resteasy.server.common.deployment.ResteasyServerCommonProcessor#processPathInterfaceImplementors","started":"01:51:19.267","dependents":[359,334,354,322],"id":276,"thread":"build-41"},{"duration":7,"stepId":"io.quarkus.deployment.pkg.steps.JarResultBuildStep#outputTarget","started":"01:51:19.050","dependents":[145],"id":105,"thread":"build-36"},{"duration":7,"stepId":"io.quarkus.arc.deployment.ArcProcessor#registerContextPropagation","started":"01:51:19.050","dependents":[223],"id":104,"thread":"build-41"},{"duration":7,"stepId":"io.quarkus.deployment.steps.ConfigGenerationBuildStep#mappings","started":"01:51:19.263","dependents":[359,414,362,360,341,339],"id":269,"thread":"build-43"},{"duration":7,"stepId":"io.quarkus.arc.deployment.SyntheticBeansProcessor#initRuntime","started":"01:51:19.501","dependents":[415,351,352,411,410,412,377],"id":349,"thread":"build-31"},{"duration":7,"stepId":"io.quarkus.hibernate.orm.deployment.HibernateOrmProcessor#build_7a4403d699506d83ac39616f3c11e5e1b448d863","started":"01:51:19.342","dependents":[415,371],"id":313,"thread":"build-20"},{"duration":7,"stepId":"io.quarkus.devui.deployment.logstream.LogStreamProcessor#createJsonRPCService","started":"01:51:19.060","dependents":[292,159],"id":128,"thread":"build-63"},{"duration":7,"stepId":"io.quarkus.smallrye.context.deployment.SmallRyeContextPropagationProcessor#transformInjectionPoint","started":"01:51:19.029","dependents":[334],"id":27,"thread":"build-9"},{"duration":7,"stepId":"io.quarkus.vertx.http.deployment.VertxHttpProcessor#additionalBeans","started":"01:51:19.030","dependents":[334,322],"id":29,"thread":"build-2"},{"duration":7,"stepId":"io.quarkus.deployment.dev.testing.TestTracingProcessor#handle","started":"01:51:19.028","dependents":[298,139],"id":18,"thread":"build-26"},{"duration":7,"stepId":"io.quarkus.agroal.deployment.AgroalProcessor#generateDataSourceBeans","started":"01:51:19.254","dependents":[415,314,350,347,305,349,377,249],"id":248,"thread":"build-43"},{"duration":7,"stepId":"io.quarkus.vertx.http.deployment.devmode.console.ConfigEditorProcessor#registerJsonRpcService","started":"01:51:19.030","dependents":[292,159],"id":30,"thread":"build-13"},{"duration":6,"stepId":"io.quarkus.deployment.steps.AdditionalClassLoaderResourcesBuildStep#appendAdditionalClassloaderResources","started":"01:51:19.040","dependents":[250],"id":53,"thread":"build-3"},{"duration":6,"stepId":"io.quarkus.devui.deployment.BuildTimeContentProcessor#createKnownInternalImportMap","started":"01:51:19.072","dependents":[399],"id":141,"thread":"build-66"},{"duration":6,"stepId":"io.quarkus.arc.deployment.ArcProcessor#unremovableAsyncObserverExceptionHandlers","started":"01:51:19.020","dependents":[359,354],"id":10,"thread":"build-10"},{"duration":6,"stepId":"io.quarkus.arc.deployment.ConfigBuildStep#generateConfigProperties","started":"01:51:19.265","dependents":[359,414,362,360,341,339],"id":271,"thread":"build-6"},{"duration":6,"stepId":"io.quarkus.vertx.http.deployment.devmode.console.DevConsoleProcessor#builder","started":"01:51:19.080","dependents":[409,393],"id":166,"thread":"build-26"},{"duration":6,"stepId":"io.quarkus.devui.deployment.DevUIProcessor#createJsonRpcRouter","started":"01:51:19.646","dependents":[415],"id":381,"thread":"build-28"},{"duration":6,"stepId":"io.quarkus.vertx.http.deployment.VertxHttpProcessor#finalizeRouter","started":"01:51:20.026","dependents":[415,411,407,410,412],"id":406,"thread":"build-40"},{"duration":6,"stepId":"io.quarkus.arc.deployment.devui.ArcDevUIProcessor#createJsonRPCService","started":"01:51:19.052","dependents":[292,159],"id":117,"thread":"build-20"},{"duration":6,"stepId":"io.quarkus.deployment.dev.IsolatedDevModeMain$5$1@2aa9e00d","started":"01:51:19.030","dependents":[334],"id":24,"thread":"build-27"},{"duration":6,"stepId":"io.quarkus.arc.deployment.ArcProcessor#convertLegacyAdditionalStereotypes","started":"01:51:19.029","dependents":[334,326],"id":26,"thread":"build-11"},{"duration":5,"stepId":"io.quarkus.arc.deployment.ConfigBuildStep#additionalBeans","started":"01:51:19.029","dependents":[334,322],"id":17,"thread":"build-20"},{"duration":5,"stepId":"io.quarkus.arc.deployment.HotDeploymentConfigBuildStep#startup","started":"01:51:19.042","dependents":[86],"id":59,"thread":"build-11"},{"duration":5,"stepId":"io.quarkus.undertow.deployment.UndertowBuildStep#addTypedAnnotations","started":"01:51:19.264","dependents":[334],"id":267,"thread":"build-46"},{"duration":5,"stepId":"io.quarkus.vertx.core.deployment.VertxCoreProcessor#overrideContextInternalInterfaceToAddSafeGuards","started":"01:51:19.042","dependents":[401],"id":62,"thread":"build-37"},{"duration":5,"stepId":"io.quarkus.deployment.steps.ReflectiveHierarchyStep#ignoreJavaClassWarnings","started":"01:51:19.018","dependents":[333],"id":7,"thread":"build-4"},{"duration":5,"stepId":"io.quarkus.netty.deployment.NettyProcessor#build","started":"01:51:19.054","dependents":[414,209],"id":118,"thread":"build-31"},{"duration":5,"stepId":"io.quarkus.resteasy.common.deployment.ResteasyCommonProcessor#addStaticInitConfigSourceProvider","started":"01:51:19.084","dependents":[382,414],"id":167,"thread":"build-17"},{"duration":5,"stepId":"io.quarkus.undertow.deployment.UndertowBuildStep#servletContainerInitializer","started":"01:51:19.265","dependents":[334,385,322],"id":270,"thread":"build-34"},{"duration":5,"stepId":"io.quarkus.vertx.http.deployment.devmode.console.DevConsoleProcessor#setupDevConsoleRoutes_0a9629c46f632dba90d4b3c7602ae4ea9d736452","started":"01:51:19.737","dependents":[405,415,409,403],"id":393,"thread":"build-40"},{"duration":5,"stepId":"io.quarkus.devservices.h2.deployment.H2DevServicesProcessor#setupH2","started":"01:51:19.039","dependents":[299],"id":52,"thread":"build-7"},{"duration":5,"stepId":"io.quarkus.hibernate.orm.panache.deployment.PanacheHibernateResourceProcessor#ensureBeanLookupAvailable","started":"01:51:19.053","dependents":[359,354],"id":109,"thread":"build-50"},{"duration":4,"stepId":"io.quarkus.hibernate.orm.deployment.HibernateOrmProcessor#registerBeans","started":"01:51:19.342","dependents":[359,334,354,322],"id":311,"thread":"build-28"},{"duration":4,"stepId":"io.quarkus.devui.deployment.BuildTimeContentProcessor#createBuildTimeData","started":"01:51:19.686","dependents":[394,399],"id":389,"thread":"build-18"},{"duration":4,"stepId":"io.quarkus.arc.deployment.ConfigBuildStep#vetoMPConfigProperties","started":"01:51:19.037","dependents":[334],"id":43,"thread":"build-9"},{"duration":4,"stepId":"io.quarkus.deployment.logging.LoggingResourceProcessor#setMinLevelForInitialConfigurator","started":"01:51:19.054","dependents":[415],"id":108,"thread":"build-51"},{"duration":4,"stepId":"io.quarkus.arc.deployment.ArcProcessor#registerSyntheticObservers","started":"01:51:19.509","dependents":[359,414,353,354,371],"id":352,"thread":"build-31"},{"duration":4,"stepId":"io.quarkus.vertx.http.deployment.HttpSecurityProcessor#setupAuthenticationMechanisms","started":"01:51:19.276","dependents":[415,334,406,371,322],"id":291,"thread":"build-53"},{"duration":4,"stepId":"io.quarkus.arc.deployment.staticmethods.InterceptedStaticMethodsProcessor#collectInterceptedStaticMethods","started":"01:51:19.498","dependents":[359,346,354,374],"id":345,"thread":"build-62"},{"duration":4,"stepId":"io.quarkus.arc.deployment.ReflectiveBeanClassesProcessor#implicitReflectiveBeanClasses","started":"01:51:19.498","dependents":[371],"id":343,"thread":"build-20"},{"duration":4,"stepId":"io.quarkus.vertx.deployment.VertxProcessor#collectEventConsumers","started":"01:51:19.498","dependents":[352,348],"id":344,"thread":"build-18"},{"duration":4,"stepId":"io.quarkus.deployment.steps.ReflectiveHierarchyStep#build","started":"01:51:19.416","dependents":[414],"id":333,"thread":"build-31"},{"duration":4,"stepId":"io.quarkus.vertx.http.deployment.devmode.console.DevConsoleProcessor#setupDevConsoleWebjar","started":"01:51:19.052","dependents":[390],"id":103,"thread":"build-35"},{"duration":4,"stepId":"io.quarkus.arc.deployment.ArcProcessor#launchMode","started":"01:51:19.018","dependents":[334,322],"id":4,"thread":"build-7"},{"duration":4,"stepId":"io.quarkus.deployment.pkg.steps.PackageTypeVerificationBuildStep#verify","started":"01:51:19.053","dependents":[411,410,412],"id":106,"thread":"build-46"},{"duration":4,"stepId":"io.quarkus.jackson.deployment.JacksonProcessor#jacksonSupport","started":"01:51:19.265","dependents":[415,350,347,349],"id":266,"thread":"build-15"},{"duration":4,"stepId":"io.quarkus.resteasy.deployment.ResteasyServletProcessor#build","started":"01:51:19.648","dependents":[415,383,414,385],"id":380,"thread":"build-75"},{"duration":3,"stepId":"io.quarkus.hibernate.orm.deployment.GraalVMFeatures#registerGeneratorClassesForReflections","started":"01:51:19.044","dependents":[414],"id":60,"thread":"build-35"},{"duration":3,"stepId":"io.quarkus.arc.deployment.ArcProcessor#loggerProducer","started":"01:51:19.055","dependents":[334,322],"id":113,"thread":"build-54"},{"duration":3,"stepId":"io.quarkus.netty.deployment.NettyProcessor#registerQualifiers","started":"01:51:19.047","dependents":[334,322],"id":73,"thread":"build-20"},{"duration":3,"stepId":"io.quarkus.vertx.http.deployment.devmode.ArcDevProcessor#registerRoutes","started":"01:51:19.538","dependents":[405,415,409,404,403,371],"id":366,"thread":"build-53"},{"duration":3,"stepId":"io.quarkus.resteasy.deployment.ResteasyStandaloneBuildStep#boot","started":"01:51:19.651","dependents":[405,415,409,403,406],"id":384,"thread":"build-20"},{"duration":3,"stepId":"io.quarkus.deployment.steps.DevModeBuildStep#watchChanges","started":"01:51:19.057","dependents":[315],"id":119,"thread":"build-55"},{"duration":3,"stepId":"io.quarkus.vertx.http.deployment.devmode.tests.TestsProcessor#handleTestResult","started":"01:51:19.046","dependents":[409,393],"id":68,"thread":"build-7"},{"duration":3,"stepId":"io.quarkus.arc.deployment.SplitPackageProcessor#splitPackageDetection","started":"01:51:19.252","dependents":[371],"id":245,"thread":"build-27"},{"duration":3,"stepId":"io.quarkus.hibernate.orm.panache.deployment.PanacheHibernateResourceProcessor#build","started":"01:51:19.855","dependents":[398,401],"id":397,"thread":"build-25"},{"duration":3,"stepId":"io.quarkus.deployment.steps.RuntimeConfigSetupBuildStep#setupRuntimeConfig","started":"01:51:19.125","dependents":[386,201,308,193,248,407,406,229,225,213,405,415,244,413,192,227,412,217,378,384,235,202,298,210,218,236,184],"id":182,"thread":"build-59"},{"duration":3,"stepId":"io.quarkus.resteasy.deployment.ResteasyStandaloneBuildStep#staticInit","started":"01:51:19.648","dependents":[415,384],"id":379,"thread":"build-44"},{"duration":3,"stepId":"io.quarkus.arc.deployment.StartupBuildSteps#addScope","started":"01:51:19.267","dependents":[328],"id":268,"thread":"build-52"},{"duration":3,"stepId":"io.quarkus.devui.deployment.menu.BuildMetricsProcessor#createBuildMetricsPages","started":"01:51:19.037","dependents":[389],"id":40,"thread":"build-27"},{"duration":3,"stepId":"io.quarkus.vertx.deployment.VertxProcessor#registerBean","started":"01:51:19.025","dependents":[334,322],"id":11,"thread":"build-20"},{"duration":3,"stepId":"io.quarkus.vertx.http.deployment.VertxHttpProcessor#shouldNotRemoveHttpServerOptionsCustomizers","started":"01:51:19.039","dependents":[359,354],"id":47,"thread":"build-13"},{"duration":3,"stepId":"io.quarkus.arc.deployment.SyntheticBeansProcessor#initStatic","started":"01:51:19.501","dependents":[415,352],"id":347,"thread":"build-17"},{"duration":3,"stepId":"io.quarkus.hibernate.orm.deployment.HibernateOrmProcessor#produceLoggingCategories","started":"01:51:19.050","dependents":[165],"id":93,"thread":"build-37"},{"duration":3,"stepId":"io.quarkus.arc.deployment.WrongAnnotationUsageProcessor#detect","started":"01:51:19.498","dependents":[371],"id":342,"thread":"build-40"},{"duration":3,"stepId":"io.quarkus.datasource.deployment.devservices.DevServicesDatasourceProcessor#launchDatabases","started":"01:51:19.315","dependents":[316,310],"id":299,"thread":"build-17"},{"duration":3,"stepId":"io.quarkus.vertx.http.deployment.devmode.tests.TestsProcessor#toggleTestOutput","started":"01:51:19.037","dependents":[409,393],"id":41,"thread":"build-11"},{"duration":3,"stepId":"io.quarkus.deployment.steps.CapabilityAggregationStep#aggregateCapabilities","started":"01:51:19.081","dependents":[288,386,379,334,246,311,161,153,305,248,249,314,380,256,154,291,329,225,242,285,289,313,168,413,155,279,216,176,195,156,332,162,385,210,167,214,238,157],"id":152,"thread":"build-12"},{"duration":3,"stepId":"io.quarkus.deployment.logging.LoggingResourceProcessor#setUpDefaultLogCleanupFilters","started":"01:51:19.071","dependents":[363],"id":139,"thread":"build-46"},{"duration":3,"stepId":"io.quarkus.undertow.deployment.UndertowBuildStep#boot","started":"01:51:19.664","dependents":[405,415,409,411,403,410,406,412],"id":386,"thread":"build-20"},{"duration":3,"stepId":"io.quarkus.vertx.deployment.VertxProcessor#build","started":"01:51:19.503","dependents":[415,414,411,410,412],"id":348,"thread":"build-20"},{"duration":3,"stepId":"io.quarkus.undertow.deployment.UndertowArcIntegrationBuildStep#beanDefiningAnnotations","started":"01:51:19.019","dependents":[283,284,334,322],"id":6,"thread":"build-5"},{"duration":3,"stepId":"io.quarkus.hibernate.orm.deployment.HibernateOrmProcessor#hotDeploymentWatchedFiles","started":"01:51:19.052","dependents":[315],"id":98,"thread":"build-4"},{"duration":2,"stepId":"io.quarkus.jdbc.h2.deployment.JDBCH2Processor#configureAgroalConnection","started":"01:51:19.084","dependents":[334,322],"id":162,"thread":"build-66"},{"duration":2,"stepId":"io.quarkus.mutiny.deployment.MutinyProcessor#runtimeInit","started":"01:51:19.154","dependents":[415],"id":222,"thread":"build-48"},{"duration":2,"stepId":"io.quarkus.arc.deployment.ConfigBuildStep#warnStaticInitInjectionPoints","started":"01:51:19.538","dependents":[363],"id":362,"thread":"build-18"},{"duration":2,"stepId":"io.quarkus.vertx.http.deployment.VertxHttpProcessor#config","started":"01:51:19.046","dependents":[382],"id":63,"thread":"build-13"},{"duration":2,"stepId":"io.quarkus.vertx.http.deployment.devmode.tests.TestsProcessor#forceRestart","started":"01:51:19.047","dependents":[409,393],"id":71,"thread":"build-36"},{"duration":2,"stepId":"io.quarkus.arc.deployment.AutoAddScopeProcessor#annotationTransformer","started":"01:51:19.373","dependents":[359,334,354],"id":328,"thread":"build-40"},{"duration":2,"stepId":"io.quarkus.hibernate.orm.deployment.dev.HibernateOrmDevServicesProcessor#devServicesAutoGenerateByDefault","started":"01:51:19.342","dependents":[310],"id":309,"thread":"build-53"},{"duration":2,"stepId":"io.quarkus.deployment.steps.BlockingOperationControlBuildStep#blockingOP","started":"01:51:19.144","dependents":[415],"id":212,"thread":"build-23"},{"duration":2,"stepId":"io.quarkus.vertx.http.deployment.StaticResourcesProcessor#runtimeInit","started":"01:51:19.646","dependents":[415,406],"id":378,"thread":"build-20"},{"duration":2,"stepId":"io.quarkus.vertx.http.deployment.VertxHttpProcessor#initializeRouter","started":"01:51:20.024","dependents":[415,406],"id":405,"thread":"build-62"},{"duration":2,"stepId":"io.quarkus.netty.deployment.NettyProcessor#limitArenaSize","started":"01:51:19.052","dependents":[415],"id":96,"thread":"build-11"},{"duration":2,"stepId":"io.quarkus.smallrye.context.deployment.SmallRyeContextPropagationProcessor#createSynthBeansForConfiguredInjectionPoints","started":"01:51:19.498","dependents":[415,350,347,349],"id":340,"thread":"build-3"},{"duration":2,"stepId":"io.quarkus.undertow.deployment.UndertowStaticResourcesBuildStep#handleGeneratedWebResources","started":"01:51:19.084","dependents":[],"id":161,"thread":"build-21"},{"duration":2,"stepId":"io.quarkus.arc.deployment.ConfigBuildStep#registerConfigMappingsBean","started":"01:51:19.498","dependents":[352],"id":341,"thread":"build-53"},{"duration":2,"stepId":"io.quarkus.vertx.http.deployment.devmode.tests.TestsProcessor#toggleInstrumentation","started":"01:51:19.048","dependents":[409,393],"id":79,"thread":"build-35"},{"duration":2,"stepId":"io.quarkus.devui.deployment.BuildTimeContentProcessor#mapPageBuildTimeData","started":"01:51:19.552","dependents":[394],"id":370,"thread":"build-5"},{"duration":2,"stepId":"io.quarkus.hibernate.orm.deployment.HibernateOrmCdiProcessor#validatePersistenceUnitExtensions","started":"01:51:19.538","dependents":[371],"id":361,"thread":"build-40"},{"duration":2,"stepId":"io.quarkus.arc.deployment.ConfigBuildStep#registerConfigPropertiesBean","started":"01:51:19.498","dependents":[352],"id":339,"thread":"build-28"},{"duration":1,"stepId":"io.quarkus.arc.deployment.ConfigBuildStep#validateConfigMappingsInjectionPoints","started":"01:51:19.538","dependents":[382,365,364],"id":359,"thread":"build-20"},{"duration":1,"stepId":"io.quarkus.smallrye.context.deployment.SmallRyeContextPropagationProcessor#registerBean","started":"01:51:19.038","dependents":[334,322],"id":38,"thread":"build-2"},{"duration":1,"stepId":"io.quarkus.credentials.CredentialsProcessor#unremoveable","started":"01:51:19.048","dependents":[359,354],"id":69,"thread":"build-37"},{"duration":1,"stepId":"io.quarkus.deployment.logging.LoggingResourceProcessor#setProperty","started":"01:51:19.019","dependents":[415],"id":2,"thread":"build-8"},{"duration":1,"stepId":"io.quarkus.deployment.steps.DevServicesConfigBuildStep#setup","started":"01:51:19.344","dependents":[321,316,411,319,363,410,412,312],"id":310,"thread":"build-3"},{"duration":1,"stepId":"io.quarkus.devui.deployment.menu.ContinuousTestingProcessor#continuousTestingState","started":"01:51:19.646","dependents":[415],"id":376,"thread":"build-43"},{"duration":1,"stepId":"io.quarkus.devui.deployment.BuildTimeContentProcessor#loadAllBuildTimeTemplates","started":"01:51:19.978","dependents":[402],"id":400,"thread":"build-76"},{"duration":1,"stepId":"io.quarkus.datasource.deployment.devservices.DevUIDatasourceProcessor#registerJsonRpcBackend","started":"01:51:19.048","dependents":[292,159],"id":70,"thread":"build-41"},{"duration":1,"stepId":"io.quarkus.hibernate.orm.deployment.HibernateOrmProcessor#build_daeea4f2c9416db083cc1423ec1bf5c757ad2a16","started":"01:51:19.342","dependents":[415,397],"id":308,"thread":"build-3"},{"duration":1,"stepId":"io.quarkus.arc.deployment.AutoProducerMethodsProcessor#annotationTransformer","started":"01:51:19.373","dependents":[334],"id":326,"thread":"build-17"},{"duration":1,"stepId":"io.quarkus.arc.deployment.ArcProcessor#feature","started":"01:51:19.018","dependents":[415],"id":3,"thread":"build-6"},{"duration":1,"stepId":"io.quarkus.hibernate.orm.deployment.HibernateOrmProcessor#registerHibernateOrmMetadataForCoreDialects","started":"01:51:19.040","dependents":[305],"id":44,"thread":"build-36"},{"duration":1,"stepId":"io.quarkus.panache.common.deployment.PanacheHibernateCommonResourceProcessor#replaceFieldAccesses","started":"01:51:19.855","dependents":[401],"id":396,"thread":"build-44"},{"duration":1,"stepId":"io.quarkus.netty.deployment.NettyProcessor#registerEventLoopBeans","started":"01:51:19.164","dependents":[415,350,347,349],"id":228,"thread":"build-31"},{"duration":1,"stepId":"io.quarkus.vertx.http.deployment.devmode.console.DevConsoleProcessor#buildTimeTemplates","started":"01:51:19.551","dependents":[411,410,412],"id":369,"thread":"build-53"},{"duration":1,"stepId":"io.quarkus.deployment.steps.DevServicesConfigBuildStep#deprecated","started":"01:51:19.049","dependents":[310],"id":75,"thread":"build-7"},{"duration":1,"stepId":"io.quarkus.panache.common.deployment.PanacheHibernateCommonResourceProcessor#findEntityClasses","started":"01:51:19.324","dependents":[396],"id":304,"thread":"build-31"},{"duration":1,"stepId":"io.quarkus.hibernate.orm.deployment.HibernateOrmProcessor#startPersistenceUnits","started":"01:51:19.646","dependents":[415,411,410,412],"id":377,"thread":"build-25"},{"duration":1,"stepId":"io.quarkus.arc.deployment.ConfigBuildStep#registerConfigClasses","started":"01:51:19.540","dependents":[415],"id":365,"thread":"build-20"},{"duration":1,"stepId":"io.quarkus.vertx.http.deployment.devmode.tests.TestsProcessor#results","started":"01:51:19.039","dependents":[369],"id":42,"thread":"build-35"},{"duration":1,"stepId":"io.quarkus.resteasy.deployment.ResteasyBuiltinsProcessor#addStaticResourcesExceptionMapper","started":"01:51:19.252","dependents":[415],"id":243,"thread":"build-43"},{"duration":1,"stepId":"io.quarkus.arc.deployment.staticmethods.InterceptedStaticMethodsProcessor#callInitializer","started":"01:51:19.646","dependents":[415],"id":374,"thread":"build-75"},{"duration":1,"stepId":"io.quarkus.deployment.steps.ConfigGenerationBuildStep#builderMappings","started":"01:51:19.540","dependents":[382,414],"id":364,"thread":"build-28"},{"duration":1,"stepId":"io.quarkus.devui.deployment.DevUIProcessor#createAllRoutes","started":"01:51:19.737","dependents":[402],"id":391,"thread":"build-18"},{"duration":1,"stepId":"io.quarkus.vertx.http.deployment.devmode.console.DevConsoleProcessor#setupDevConsoleRoutes_8bb86a3e770caadb970f4facb490e30df7a2a187","started":"01:51:19.737","dependents":[405,415,409,403],"id":392,"thread":"build-44"},{"duration":1,"stepId":"io.quarkus.vertx.deployment.EventBusCodecProcessor#registerCodecs","started":"01:51:19.373","dependents":[414,348],"id":327,"thread":"build-18"},{"duration":1,"stepId":"io.quarkus.deployment.steps.CurateOutcomeBuildStep#curateOutcome","started":"01:51:19.058","dependents":[390,369,231,299,147,401,143,319,292,191,176,121,409,284,241,152,394,290,134,370,393,387],"id":115,"thread":"build-59"},{"duration":1,"stepId":"io.quarkus.devui.deployment.build.BuildMetricsDevUIProcessor#createJsonRPCService","started":"01:51:19.027","dependents":[292,159],"id":14,"thread":"build-27"},{"duration":1,"stepId":"io.quarkus.resteasy.deployment.ResteasyServletProcessor#addServletsToExceptionMapper","started":"01:51:19.653","dependents":[415],"id":383,"thread":"build-44"},{"duration":1,"stepId":"io.quarkus.arc.deployment.ConfigBuildStep#validateConfigPropertiesInjectionPoints","started":"01:51:19.538","dependents":[365],"id":360,"thread":"build-3"},{"duration":1,"stepId":"io.quarkus.hibernate.orm.deployment.dev.HibernateOrmDevUIProcessor#create","started":"01:51:19.039","dependents":[370,387],"id":39,"thread":"build-4"},{"duration":1,"stepId":"io.quarkus.narayana.jta.deployment.NarayanaJtaProcessor#registerScope","started":"01:51:19.057","dependents":[265],"id":112,"thread":"build-46"},{"duration":1,"stepId":"io.quarkus.vertx.http.deployment.devmode.console.ConfigEditorProcessor#handleRequests","started":"01:51:19.346","dependents":[409,393],"id":312,"thread":"build-40"},{"duration":1,"stepId":"io.quarkus.arc.deployment.devui.ArcDevUIProcessor#pages","started":"01:51:19.551","dependents":[370,387],"id":368,"thread":"build-28"},{"duration":1,"stepId":"io.quarkus.vertx.http.deployment.VertxHttpProcessor#openSocket","started":"01:51:20.239","dependents":[415,414],"id":413,"thread":"build-65"},{"duration":1,"stepId":"io.quarkus.arc.deployment.ArcProcessor#signalBeanContainerReady","started":"01:51:19.645","dependents":[415,378,375,385,373,381,376,406,412,377,374],"id":372,"thread":"build-48"},{"duration":1,"stepId":"io.quarkus.hibernate.orm.deployment.HibernateOrmProcessor#jpaEntitiesIndexer","started":"01:51:19.264","dependents":[408,300],"id":260,"thread":"build-41"},{"duration":1,"stepId":"io.quarkus.resteasy.common.deployment.ResteasyCommonProcessor#setupResteasyInjection","started":"01:51:19.646","dependents":[415,380,379],"id":375,"thread":"build-50"},{"duration":0,"stepId":"io.quarkus.datasource.deployment.devservices.DevUIDatasourceProcessor#create","started":"01:51:19.052","dependents":[370,387],"id":89,"thread":"build-20"},{"duration":0,"stepId":"io.quarkus.deployment.JniProcessor#setupJni","started":"01:51:19.059","dependents":[209],"id":114,"thread":"build-60"},{"duration":0,"stepId":"io.quarkus.deployment.steps.ConfigGenerationBuildStep#runtimeDefaultsConfig","started":"01:51:19.541","dependents":[382,414],"id":363,"thread":"build-40"},{"duration":0,"stepId":"io.quarkus.deployment.console.ConsoleProcessor#installCliCommands","started":"01:51:19.357","dependents":[411,410,412],"id":320,"thread":"build-18"},{"duration":0,"stepId":"io.quarkus.vertx.core.deployment.VertxCoreProcessor#cleanupVertxWarnings","started":"01:51:19.036","dependents":[298,139],"id":23,"thread":"build-24"},{"duration":0,"stepId":"io.quarkus.hibernate.orm.panache.common.deployment.PanacheJpaCommonResourceProcessor#lookupNamedQueries_5a86a91ed8ef1aa483288c8239df231983eeb766","started":"01:51:19.324","dependents":[303],"id":302,"thread":"build-18"},{"duration":0,"stepId":"io.quarkus.resteasy.deployment.ResteasyServletProcessor#webXmlMapping","started":"01:51:19.298","dependents":[330],"id":295,"thread":"build-62"},{"duration":0,"stepId":"io.quarkus.deployment.console.ConsoleProcessor#setupExceptionHandler","started":"01:51:19.230","dependents":[247],"id":239,"thread":"build-28"},{"duration":0,"stepId":"io.quarkus.deployment.steps.ProfileBuildStep#defaultProfile","started":"01:51:19.050","dependents":[363],"id":72,"thread":"build-43"},{"duration":0,"stepId":"io.quarkus.deployment.steps.CurateOutcomeBuildStep#removeResources","started":"01:51:19.060","dependents":[401],"id":121,"thread":"build-55"},{"duration":0,"stepId":"io.quarkus.hibernate.orm.deployment.HibernateOrmProcessor#candidatesForFieldAccess","started":"01:51:19.324","dependents":[304],"id":301,"thread":"build-17"},{"duration":0,"stepId":"io.quarkus.resteasy.jackson.deployment.ResteasyJacksonProcessor#feature","started":"01:51:19.029","dependents":[415],"id":15,"thread":"build-7"},{"duration":0,"stepId":"io.quarkus.deployment.index.ApplicationArchiveBuildStep#addConfiguredIndexedDependencies","started":"01:51:19.055","dependents":[241],"id":97,"thread":"build-53"},{"duration":0,"stepId":"io.quarkus.arc.deployment.ArcProcessor#quarkusApplication","started":"01:51:19.265","dependents":[334,322],"id":259,"thread":"build-31"},{"duration":0,"stepId":"io.quarkus.arc.deployment.init.InitializationTaskProcessor#startApplicationInitializer","started":"01:51:19.509","dependents":[415],"id":351,"thread":"build-20"},{"duration":0,"stepId":"io.quarkus.arc.deployment.ArcProcessor#marker","started":"01:51:19.038","dependents":[241],"id":35,"thread":"build-12"},{"duration":0,"stepId":"io.quarkus.hibernate.orm.panache.deployment.PanacheHibernateResourceProcessor#produceModel","started":"01:51:19.020","dependents":[395,260],"id":1,"thread":"build-11"},{"duration":0,"stepId":"io.quarkus.narayana.jta.deployment.NarayanaJtaProcessor#transactionContext","started":"01:51:19.427","dependents":[337],"id":336,"thread":"build-40"},{"duration":0,"stepId":"io.quarkus.jdbc.h2.deployment.H2JDBCReflections#build","started":"01:51:19.061","dependents":[414],"id":123,"thread":"build-67"},{"duration":0,"stepId":"io.quarkus.arc.deployment.AutoInjectFieldProcessor#autoInjectQualifiers","started":"01:51:19.373","dependents":[330,325,328],"id":323,"thread":"build-53"},{"duration":0,"stepId":"io.quarkus.hibernate.orm.deployment.HibernateOrmProcessor#multitenancy","started":"01:51:19.342","dependents":[415,359,350,347,354,349],"id":306,"thread":"build-62"},{"duration":0,"stepId":"io.quarkus.hibernate.orm.deployment.HibernateOrmProcessor#contributeQuarkusConfigToJpaModel","started":"01:51:19.051","dependents":[300],"id":84,"thread":"build-43"},{"duration":0,"stepId":"io.quarkus.deployment.logging.LoggingWithPanacheProcessor#process","started":"01:51:19.265","dependents":[401],"id":263,"thread":"build-57"},{"duration":0,"stepId":"io.quarkus.vertx.http.deployment.devmode.console.DevConsoleProcessor#config","started":"01:51:19.355","dependents":[369],"id":317,"thread":"build-17"},{"duration":0,"stepId":"io.quarkus.deployment.console.ConsoleProcessor#missingDevUIMessageHandler","started":"01:51:19.230","dependents":[411,410,412],"id":238,"thread":"build-27"},{"duration":0,"stepId":"io.quarkus.vertx.http.deployment.devmode.console.DevConsoleProcessor#runtimeTemplates","started":"01:51:20.238","dependents":[415],"id":411,"thread":"build-65"},{"duration":0,"stepId":"io.quarkus.jdbc.h2.deployment.JDBCH2Processor#registerDefaultDbType","started":"01:51:19.048","dependents":[176,299],"id":64,"thread":"build-6"},{"duration":0,"stepId":"io.quarkus.resteasy.deployment.RestPathAnnotationProcessor#findRestPaths","started":"01:51:19.416","dependents":[334],"id":332,"thread":"build-40"},{"duration":0,"stepId":"io.quarkus.arc.deployment.ConfigBuildStep#validateConfigInjectionPoints","started":"01:51:19.538","dependents":[373],"id":355,"thread":"build-49"},{"duration":0,"stepId":"io.quarkus.vertx.core.deployment.VertxCoreProcessor#preventLoggerContention","started":"01:51:19.054","dependents":[165],"id":95,"thread":"build-52"},{"duration":0,"stepId":"io.quarkus.deployment.ForkJoinPoolProcessor#setProperty","started":"01:51:19.025","dependents":[415],"id":8,"thread":"build-22"},{"duration":0,"stepId":"io.quarkus.vertx.http.deployment.StaticResourcesProcessor#collectStaticResources","started":"01:51:19.252","dependents":[378],"id":242,"thread":"build-31"},{"duration":0,"stepId":"io.quarkus.config.yaml.deployment.ConfigYamlProcessor#watchYamlConfig","started":"01:51:19.046","dependents":[315],"id":55,"thread":"build-20"},{"duration":0,"stepId":"io.quarkus.vertx.deployment.VertxProcessor#featureAndCapability","started":"01:51:19.052","dependents":[415,152],"id":91,"thread":"build-38"},{"duration":0,"stepId":"io.quarkus.arc.deployment.BuildTimeEnabledProcessor#unlessBuildProfile","started":"01:51:19.263","dependents":[330,275],"id":251,"thread":"build-27"},{"duration":0,"stepId":"io.quarkus.hibernate.orm.panache.deployment.PanacheHibernateResourceProcessor#marker","started":"01:51:19.044","dependents":[241],"id":49,"thread":"build-36"},{"duration":0,"stepId":"io.quarkus.undertow.deployment.UndertowLogFilterBuildStep#setupLogFilters","started":"01:51:19.036","dependents":[298,139],"id":22,"thread":"build-25"},{"duration":0,"stepId":"io.quarkus.hibernate.orm.panache.common.deployment.PanacheJpaCommonResourceProcessor#buildNamedQueryMap","started":"01:51:19.325","dependents":[415],"id":303,"thread":"build-17"},{"duration":0,"stepId":"io.quarkus.narayana.jta.deployment.NarayanaJtaProcessor#logCleanupFilters","started":"01:51:19.042","dependents":[298,139],"id":46,"thread":"build-35"},{"duration":0,"stepId":"io.quarkus.deployment.recording.AnnotationProxyBuildStep#build","started":"01:51:19.172","dependents":[348],"id":232,"thread":"build-27"},{"duration":0,"stepId":"io.quarkus.undertow.deployment.UndertowBuildStep#registerContext","started":"01:51:19.427","dependents":[337],"id":335,"thread":"build-31"},{"duration":0,"stepId":"io.quarkus.hibernate.orm.deployment.HibernateOrmProcessor#enrollBeanValidationTypeSafeActivatorForReflection","started":"01:51:19.084","dependents":[414],"id":153,"thread":"build-14"},{"duration":0,"stepId":"io.quarkus.arc.deployment.LookupConditionsProcessor#suppressConditionsGenerators","started":"01:51:19.373","dependents":[334],"id":324,"thread":"build-62"},{"duration":0,"stepId":"io.quarkus.resteasy.deployment.ResteasyBuiltinsProcessor#addAdditionalEndpointsExceptionMapper","started":"01:51:20.024","dependents":[415],"id":404,"thread":"build-40"},{"duration":0,"stepId":"io.quarkus.resteasy.deployment.ResteasyServletProcessor#jaxrsConfig","started":"01:51:19.416","dependents":[332],"id":331,"thread":"build-18"},{"duration":0,"stepId":"io.quarkus.arc.deployment.ExecutorServiceProcessor#executorServiceBean","started":"01:51:19.154","dependents":[350,347,349],"id":219,"thread":"build-57"},{"duration":0,"stepId":"io.quarkus.undertow.deployment.UndertowBuildStep#customScope","started":"01:51:19.265","dependents":[265],"id":264,"thread":"build-24"},{"duration":0,"stepId":"io.quarkus.arc.deployment.LifecycleEventsBuildStep#startupEvent","started":"01:51:20.238","dependents":[415,413],"id":412,"thread":"build-40"},{"duration":0,"stepId":"io.quarkus.hibernate.orm.deployment.HibernateOrmProcessor#includeArchivesHostingEntityPackagesInIndex","started":"01:51:19.055","dependents":[241],"id":99,"thread":"build-53"},{"duration":0,"stepId":"io.quarkus.deployment.ConstructorPropertiesProcessor#build","started":"01:51:19.264","dependents":[414],"id":255,"thread":"build-31"},{"duration":0,"stepId":"io.quarkus.resteasy.server.common.deployment.ResteasyServerCommonProcessor#registerCompatibleAnnotationPrefixes","started":"01:51:19.051","dependents":[330],"id":78,"thread":"build-7"},{"duration":0,"stepId":"io.quarkus.hibernate.orm.panache.deployment.PanacheHibernateResourceProcessor#featureBuildItem","started":"01:51:19.059","dependents":[415],"id":111,"thread":"build-60"},{"duration":0,"stepId":"io.quarkus.resteasy.common.deployment.ResteasyCommonProcessor#resteasyConfig","started":"01:51:19.084","dependents":[329],"id":154,"thread":"build-36"},{"duration":0,"stepId":"io.quarkus.undertow.deployment.UndertowBuildStep#setupCapability","started":"01:51:19.263","dependents":[415],"id":252,"thread":"build-43"},{"duration":0,"stepId":"io.quarkus.arc.deployment.ArcProcessor#setupExecutor","started":"01:51:19.154","dependents":[415],"id":220,"thread":"build-46"},{"duration":0,"stepId":"io.quarkus.undertow.deployment.UndertowBuildStep#configInjectionStaticInitAnnotations","started":"01:51:19.265","dependents":[362],"id":261,"thread":"build-33"},{"duration":0,"stepId":"io.quarkus.deployment.ExtensionLoader#booleanSupplierFactory","started":"01:51:19.038","dependents":[147],"id":37,"thread":"build-3"},{"duration":0,"stepId":"io.quarkus.hibernate.orm.panache.deployment.PanacheHibernateResourceProcessor#validate","started":"01:51:19.538","dependents":[371],"id":358,"thread":"build-28"},{"duration":0,"stepId":"io.quarkus.devui.deployment.menu.ContinuousTestingProcessor#createContinuousTestingPages","started":"01:51:19.046","dependents":[389],"id":54,"thread":"build-36"},{"duration":0,"stepId":"io.quarkus.hibernate.orm.deployment.HibernateLogFilterBuildStep#setupLogFilters","started":"01:51:19.060","dependents":[298,139],"id":122,"thread":"build-55"},{"duration":0,"stepId":"io.quarkus.config.yaml.deployment.ConfigYamlProcessor#feature","started":"01:51:19.019","dependents":[415],"id":5,"thread":"build-9"},{"duration":0,"stepId":"io.quarkus.hibernate.orm.deployment.HibernateUserTypeProcessor#build","started":"01:51:19.264","dependents":[414],"id":257,"thread":"build-18"},{"duration":0,"stepId":"io.quarkus.deployment.steps.ConfigGenerationBuildStep#suppressNonRuntimeConfigChanged","started":"01:51:19.048","dependents":[217],"id":65,"thread":"build-13"},{"duration":0,"stepId":"io.quarkus.deployment.steps.ConfigGenerationBuildStep#staticInitSources","started":"01:51:19.058","dependents":[382],"id":110,"thread":"build-50"},{"duration":0,"stepId":"io.quarkus.devui.deployment.menu.ExtensionsProcessor#createExtensionsPages","started":"01:51:19.686","dependents":[389],"id":388,"thread":"build-25"},{"duration":0,"stepId":"io.quarkus.vertx.http.deployment.ManagementInterfaceSecurityProcessor#builtins","started":"01:51:19.056","dependents":[334,322],"id":100,"thread":"build-55"},{"duration":0,"stepId":"io.quarkus.undertow.deployment.UndertowBuildStep#contextPath","started":"01:51:19.298","dependents":[386,380,385],"id":296,"thread":"build-40"},{"duration":0,"stepId":"io.quarkus.resteasy.common.deployment.ResteasyCommonProcessor#configInjectionStaticInitProvider","started":"01:51:19.051","dependents":[362],"id":83,"thread":"build-47"},{"duration":0,"stepId":"io.quarkus.hibernate.orm.deployment.HibernateOrmProcessor#defineTypeOfImpliedPU","started":"01:51:19.261","dependents":[307,314,305],"id":249,"thread":"build-47"},{"duration":0,"stepId":"io.quarkus.deployment.steps.MainClassBuildStep#applicationReflection","started":"01:51:19.042","dependents":[414],"id":45,"thread":"build-36"},{"duration":0,"stepId":"io.quarkus.arc.deployment.TestsAsBeansProcessor#testAnnotations","started":"01:51:19.057","dependents":[283,284,334,322],"id":107,"thread":"build-36"},{"duration":0,"stepId":"io.quarkus.hibernate.orm.panache.deployment.PanacheHibernateResourceProcessor#recordEntityToPersistenceUnit","started":"01:51:19.859","dependents":[415],"id":398,"thread":"build-44"},{"duration":0,"stepId":"io.quarkus.hibernate.orm.deployment.HibernateOrmCdiProcessor#convertJpaResourceAnnotationsToQualifier","started":"01:51:19.342","dependents":[334],"id":307,"thread":"build-31"},{"duration":0,"stepId":"io.quarkus.arc.deployment.ArcProcessor#validateAsyncObserverExceptionHandlers","started":"01:51:19.538","dependents":[371],"id":356,"thread":"build-17"},{"duration":0,"stepId":"io.quarkus.arc.deployment.TestsAsBeansProcessor#testClassBeans","started":"01:51:19.060","dependents":[334,322],"id":120,"thread":"build-55"},{"duration":0,"stepId":"io.quarkus.undertow.deployment.UndertowBuildStep#produceIdentityManager","started":"01:51:19.264","dependents":[334,322],"id":256,"thread":"build-6"},{"duration":0,"stepId":"io.quarkus.datasource.deployment.devservices.DevUIDatasourceProcessor#devConsoleInfo","started":"01:51:19.049","dependents":[369],"id":67,"thread":"build-22"},{"duration":0,"stepId":"io.quarkus.deployment.steps.PreloadClassesBuildStep#registerPreInitClasses","started":"01:51:19.037","dependents":[],"id":28,"thread":"build-12"},{"duration":0,"stepId":"io.quarkus.hibernate.orm.deployment.HibernateOrmProcessor#contributePersistenceXmlToJpaModel","started":"01:51:19.181","dependents":[300],"id":234,"thread":"build-27"},{"duration":0,"stepId":"io.quarkus.resteasy.common.deployment.ResteasyCommonProcessor#disableDefaultExceptionMapper","started":"01:51:19.052","dependents":[415],"id":88,"thread":"build-35"},{"duration":0,"stepId":"io.quarkus.deployment.steps.BannerProcessor#watchBannerChanges","started":"01:51:19.052","dependents":[315],"id":87,"thread":"build-46"},{"duration":0,"stepId":"io.quarkus.jdbc.h2.deployment.JDBCH2Processor#registerDriver","started":"01:51:19.051","dependents":[176],"id":77,"thread":"build-20"},{"duration":0,"stepId":"io.quarkus.arc.deployment.ArcProcessor#exposeCustomScopeNames","started":"01:51:19.266","dependents":[283,342,268,284,334,330,326,328,322,276],"id":265,"thread":"build-57"},{"duration":0,"stepId":"io.quarkus.deployment.steps.ShutdownListenerBuildStep#setupShutdown","started":"01:51:20.032","dependents":[415],"id":407,"thread":"build-62"},{"duration":0,"stepId":"io.quarkus.arc.deployment.BuildTimeEnabledProcessor#ifBuildProfile","started":"01:51:19.265","dependents":[330,275],"id":262,"thread":"build-52"},{"duration":0,"stepId":"io.quarkus.deployment.dev.ConfigureDisableInstrumentationBuildStep#configure","started":"01:51:19.051","dependents":[411,410,412],"id":86,"thread":"build-46"},{"duration":0,"stepId":"io.quarkus.arc.deployment.ConfigBuildStep#registerCustomConfigBeanTypes","started":"01:51:19.498","dependents":[414,350,347,349],"id":338,"thread":"build-17"},{"duration":0,"stepId":"io.quarkus.arc.deployment.BuildTimeEnabledProcessor#conditionTransformer","started":"01:51:19.274","dependents":[334],"id":275,"thread":"build-23"},{"duration":0,"stepId":"io.quarkus.arc.deployment.StartupBuildSteps#registerStartupObservers","started":"01:51:19.513","dependents":[354],"id":353,"thread":"build-20"},{"duration":0,"stepId":"io.quarkus.arc.deployment.ObserverValidationProcessor#validateApplicationObserver","started":"01:51:19.538","dependents":[371],"id":357,"thread":"build-35"},{"duration":0,"stepId":"io.quarkus.agroal.deployment.AgroalProcessor#agroal","started":"01:51:19.029","dependents":[415],"id":16,"thread":"build-11"},{"duration":0,"stepId":"io.quarkus.arc.deployment.HotDeploymentConfigBuildStep#configFile","started":"01:51:19.051","dependents":[315],"id":82,"thread":"build-20"},{"duration":0,"stepId":"io.quarkus.arc.deployment.ConfigBuildStep#validateConfigValues","started":"01:51:19.646","dependents":[415,414],"id":373,"thread":"build-44"},{"duration":0,"stepId":"io.quarkus.vertx.http.deployment.VertxHttpProcessor#notFoundRoutes","started":"01:51:20.024","dependents":[404],"id":403,"thread":"build-54"},{"duration":0,"stepId":"io.quarkus.deployment.SslProcessor#setupNativeSsl","started":"01:51:19.050","dependents":[209,77,248,216],"id":74,"thread":"build-44"},{"duration":0,"stepId":"io.quarkus.devui.deployment.menu.DevServicesProcessor#createDevServicesPages","started":"01:51:19.355","dependents":[389],"id":318,"thread":"build-18"},{"duration":0,"stepId":"io.quarkus.hibernate.orm.deployment.HibernateOrmProcessor#checkTransactionsSupport","started":"01:51:19.084","dependents":[371],"id":157,"thread":"build-38"},{"duration":0,"stepId":"io.quarkus.jackson.deployment.JacksonProcessor#autoRegisterModules","started":"01:51:19.264","dependents":[287],"id":253,"thread":"build-45"},{"duration":0,"stepId":"io.quarkus.hibernate.orm.panache.deployment.PanacheHibernateResourceProcessor#collectEntityClasses","started":"01:51:19.263","dependents":[397],"id":254,"thread":"build-24"},{"duration":0,"stepId":"io.quarkus.resteasy.common.deployment.ResteasyCommonProcessor#setupGzipProviders","started":"01:51:19.059","dependents":[329],"id":116,"thread":"build-61"},{"duration":0,"stepId":"io.quarkus.hibernate.orm.deployment.HibernateOrmProcessor#addPersistenceUnitAnnotationToIndex","started":"01:51:19.038","dependents":[250],"id":34,"thread":"build-13"},{"duration":0,"stepId":"io.quarkus.vertx.core.deployment.VertxCoreProcessor#filterNettyHostsFileParsingWarn","started":"01:51:19.048","dependents":[298,139],"id":61,"thread":"build-35"},{"duration":0,"stepId":"io.quarkus.jdbc.h2.deployment.JDBCH2Processor#feature","started":"01:51:19.056","dependents":[415],"id":101,"thread":"build-55"},{"duration":0,"stepId":"io.quarkus.arc.deployment.staticmethods.InterceptedStaticMethodsProcessor#processInterceptedStaticMethods","started":"01:51:19.503","dependents":[414,395,401],"id":346,"thread":"build-18"},{"duration":0,"stepId":"io.quarkus.undertow.deployment.WebXmlParsingBuildStep#marker","started":"01:51:19.044","dependents":[241],"id":48,"thread":"build-13"},{"duration":0,"stepId":"io.quarkus.undertow.deployment.WebXmlParsingBuildStep#configFile","started":"01:51:19.026","dependents":[315],"id":9,"thread":"build-23"},{"duration":0,"stepId":"io.quarkus.hibernate.orm.deployment.HibernateOrmAlwaysEnabledProcessor#featureBuildItem","started":"01:51:19.052","dependents":[415],"id":92,"thread":"build-46"},{"duration":0,"stepId":"io.quarkus.arc.deployment.AutoInjectFieldProcessor#annotationTransformer","started":"01:51:19.373","dependents":[334],"id":325,"thread":"build-20"},{"duration":0,"stepId":"io.quarkus.deployment.steps.ApplicationInfoBuildStep#create","started":"01:51:19.051","dependents":[415],"id":80,"thread":"build-11"},{"duration":0,"stepId":"io.quarkus.deployment.logging.LoggingResourceProcessor#setUpDefaultLevels","started":"01:51:19.086","dependents":[298,363],"id":165,"thread":"build-32"},{"duration":0,"stepId":"io.quarkus.agroal.deployment.AgroalProcessor#adaptOpenTelemetryJdbcInstrumentationForNative","started":"01:51:19.084","dependents":[401],"id":156,"thread":"build-10"},{"duration":0,"stepId":"io.quarkus.deployment.pkg.steps.PackageTypeVerificationBuildStep#builtins","started":"01:51:19.051","dependents":[106],"id":81,"thread":"build-35"},{"duration":0,"stepId":"io.quarkus.hibernate.orm.deployment.HibernateOrmProcessor#warnOfSchemaProblems","started":"01:51:20.238","dependents":[415],"id":410,"thread":"build-62"},{"duration":0,"stepId":"io.quarkus.resteasy.deployment.RestPathAnnotationProcessor#registerBeanClasses","started":"01:51:19.084","dependents":[334,322],"id":155,"thread":"build-60"},{"duration":0,"stepId":"io.quarkus.deployment.steps.ReflectionDiagnosticProcessor#writeReflectionData","started":"01:51:20.240","dependents":[],"id":414,"thread":"build-62"},{"duration":0,"stepId":"io.quarkus.caffeine.deployment.CaffeineProcessor#cacheLoaders","started":"01:51:19.264","dependents":[414],"id":258,"thread":"build-57"}],"started":"2023-05-18T01:51:19.016","items":[{"count":744,"class":"io.quarkus.deployment.builditem.ConfigDescriptionBuildItem"},{"count":232,"class":"io.quarkus.deployment.builditem.GeneratedClassBuildItem"},{"count":111,"class":"io.quarkus.deployment.builditem.nativeimage.ReflectiveClassBuildItem"},{"count":70,"class":"io.quarkus.deployment.builditem.BytecodeTransformerBuildItem"},{"count":58,"class":"io.quarkus.deployment.builditem.MainBytecodeRecorderBuildItem"},{"count":46,"class":"io.quarkus.arc.deployment.SyntheticBeanBuildItem"},{"count":40,"class":"io.quarkus.deployment.builditem.StaticBytecodeRecorderBuildItem"},{"count":36,"class":"io.quarkus.vertx.http.deployment.devmode.console.DevTemplatePathBuildItem"},{"count":35,"class":"io.quarkus.deployment.builditem.nativeimage.RuntimeInitializedClassBuildItem"},{"count":34,"class":"io.quarkus.arc.deployment.AdditionalBeanBuildItem"},{"count":32,"class":"io.quarkus.vertx.http.deployment.RouteBuildItem"},{"count":27,"class":"io.quarkus.deployment.builditem.nativeimage.ReflectiveHierarchyBuildItem"},{"count":25,"class":"io.quarkus.deployment.builditem.HotDeploymentWatchedFileBuildItem"},{"count":24,"class":"io.quarkus.deployment.builditem.nativeimage.ReflectiveMethodBuildItem"},{"count":23,"class":"io.quarkus.deployment.builditem.RunTimeConfigurationDefaultBuildItem"},{"count":20,"class":"io.quarkus.devconsole.spi.DevConsoleRouteBuildItem"},{"count":17,"class":"io.quarkus.deployment.logging.LogCleanupFilterBuildItem"},{"count":16,"class":"io.quarkus.arc.deployment.UnremovableBeanBuildItem"},{"count":14,"class":"io.quarkus.deployment.builditem.CapabilityBuildItem"},{"count":13,"class":"io.quarkus.resteasy.common.spi.ResteasyJaxrsProviderBuildItem"},{"count":12,"class":"io.quarkus.deployment.builditem.FeatureBuildItem"},{"count":10,"class":"io.quarkus.deployment.builditem.AdditionalApplicationArchiveMarkerBuildItem"},{"count":8,"class":"io.quarkus.resteasy.server.common.spi.AllowedJaxRsAnnotationPrefixBuildItem"},{"count":8,"class":"io.quarkus.arc.deployment.BeanDefiningAnnotationBuildItem"},{"count":8,"class":"io.quarkus.deployment.builditem.AdditionalIndexedClassesBuildItem"},{"count":8,"class":"io.quarkus.hibernate.orm.deployment.spi.DatabaseKindDialectBuildItem"},{"count":7,"class":"io.quarkus.arc.deployment.AnnotationsTransformerBuildItem"},{"count":7,"class":"io.quarkus.devui.spi.JsonRPCProvidersBuildItem"},{"count":7,"class":"io.quarkus.deployment.pkg.builditem.PackageTypeBuildItem"},{"count":6,"class":"io.quarkus.deployment.builditem.SystemPropertyBuildItem"},{"count":6,"class":"io.quarkus.undertow.deployment.ServletInitParamBuildItem"},{"count":6,"class":"io.quarkus.deployment.builditem.ConsoleCommandBuildItem"},{"count":6,"class":"io.quarkus.vertx.http.deployment.webjar.WebJarBuildItem"},{"count":6,"class":"io.quarkus.deployment.builditem.nativeimage.NativeImageSystemPropertyBuildItem"},{"count":5,"class":"io.quarkus.devui.deployment.InternalPageBuildItem"},{"count":5,"class":"io.quarkus.devui.deployment.DevUIWebJarBuildItem"},{"count":5,"class":"io.quarkus.deployment.builditem.RunTimeConfigBuilderBuildItem"},{"count":5,"class":"io.quarkus.deployment.builditem.StaticInitConfigBuilderBuildItem"},{"count":5,"class":"io.quarkus.deployment.builditem.SuppressNonRuntimeConfigChangedWarningBuildItem"},{"count":5,"class":"io.quarkus.vertx.http.deployment.devmode.NotFoundPageDisplayableEndpointBuildItem"},{"count":5,"class":"io.quarkus.devconsole.spi.DevConsoleTemplateInfoBuildItem"},{"count":5,"class":"io.quarkus.devui.deployment.BuildTimeConstBuildItem"},{"count":5,"class":"io.quarkus.hibernate.orm.panache.common.deployment.PanacheNamedQueryEntityClassBuildStep"},{"count":5,"class":"io.quarkus.deployment.builditem.nativeimage.ReflectiveFieldBuildItem"},{"count":5,"class":"io.quarkus.deployment.builditem.ServiceStartBuildItem"},{"count":5,"class":"io.quarkus.devui.deployment.DevUIRoutesBuildItem"},{"count":4,"class":"io.quarkus.devconsole.spi.DevConsoleRuntimeTemplateInfoBuildItem"},{"count":4,"class":"io.quarkus.devui.spi.page.CardPageBuildItem"},{"count":3,"class":"io.quarkus.deployment.builditem.ObjectSubstitutionBuildItem"},{"count":3,"class":"io.quarkus.jackson.spi.ClassPathJacksonModuleBuildItem"},{"count":3,"class":"io.quarkus.vertx.http.deployment.HttpSecurityPolicyBuildItem"},{"count":3,"class":"io.quarkus.hibernate.orm.panache.deployment.EntityToPersistenceUnitBuildItem"},{"count":2,"class":"io.quarkus.deployment.builditem.ShutdownListenerBuildItem"},{"count":2,"class":"io.quarkus.hibernate.orm.panache.deployment.PanacheEntityClassBuildItem"},{"count":2,"class":"io.quarkus.vertx.http.deployment.FilterBuildItem"},{"count":2,"class":"io.quarkus.arc.deployment.AutoAddScopeBuildItem"},{"count":2,"class":"io.quarkus.devui.spi.buildtime.QuteTemplateBuildItem"},{"count":2,"class":"io.quarkus.deployment.builditem.nativeimage.NativeImageConfigBuildItem"},{"count":2,"class":"io.quarkus.deployment.dev.testing.TestListenerBuildItem"},{"count":2,"class":"io.quarkus.deployment.builditem.nativeimage.NativeImageResourceBuildItem"},{"count":2,"class":"io.quarkus.deployment.builditem.BytecodeRecorderObjectLoaderBuildItem"},{"count":2,"class":"io.quarkus.arc.deployment.ConfigInjectionStaticInitBuildItem"},{"count":2,"class":"io.quarkus.arc.deployment.CustomScopeBuildItem"},{"count":2,"class":"io.quarkus.devui.spi.buildtime.StaticContentBuildItem"},{"count":2,"class":"io.quarkus.arc.deployment.ContextRegistrationPhaseBuildItem$ContextConfiguratorBuildItem"},{"count":2,"class":"io.quarkus.devui.deployment.InternalImportMapBuildItem"},{"count":2,"class":"io.quarkus.deployment.builditem.LogCategoryBuildItem"},{"count":1,"class":"io.quarkus.devui.deployment.MvnpmBuildItem"},{"count":1,"class":"io.quarkus.deployment.builditem.AnnotationProxyBuildItem"},{"count":1,"class":"io.quarkus.deployment.builditem.TransformedClassesBuildItem"},{"count":1,"class":"io.quarkus.deployment.builditem.BytecodeRecorderConstantDefinitionBuildItem"},{"count":1,"class":"io.quarkus.hibernate.orm.deployment.JpaModelIndexBuildItem"},{"count":1,"class":"io.quarkus.arc.deployment.devui.ArcBeanInfoBuildItem"},{"count":1,"class":"io.quarkus.datasource.deployment.spi.DevServicesDatasourceConfigurationHandlerBuildItem"},{"count":1,"class":"io.quarkus.deployment.console.ConsoleInstalledBuildItem"},{"count":1,"class":"io.quarkus.arc.deployment.BeanDiscoveryFinishedBuildItem"},{"count":1,"class":"io.quarkus.resteasy.common.spi.ResteasyConfigBuildItem"},{"count":1,"class":"io.quarkus.deployment.builditem.RunTimeConfigurationProxyBuildItem"},{"count":1,"class":"io.quarkus.arc.deployment.SynthesisFinishedBuildItem"},{"count":1,"class":"io.quarkus.vertx.http.deployment.DefaultRouteBuildItem"},{"count":1,"class":"io.quarkus.vertx.core.deployment.EventLoopCountBuildItem"},{"count":1,"class":"io.quarkus.resteasy.common.deployment.JaxrsProvidersToRegisterBuildItem"},{"count":1,"class":"io.quarkus.vertx.core.deployment.CoreVertxBuildItem"},{"count":1,"class":"io.quarkus.arc.deployment.BuildCompatibleExtensionsBuildItem"},{"count":1,"class":"io.quarkus.devui.deployment.ThemeVarsBuildItem"},{"count":1,"class":"io.quarkus.datasource.deployment.spi.DefaultDataSourceDbKindBuildItem"},{"count":1,"class":"io.quarkus.hibernate.orm.deployment.JpaModelPersistenceUnitMappingBuildItem"},{"count":1,"class":"io.quarkus.deployment.builditem.DockerStatusBuildItem"},{"count":1,"class":"io.quarkus.deployment.builditem.nativeimage.ReflectiveHierarchyIgnoreWarningBuildItem"},{"count":1,"class":"io.quarkus.arc.deployment.InterceptorResolverBuildItem"},{"count":1,"class":"io.quarkus.vertx.http.deployment.InitialRouterBuildItem"},{"count":1,"class":"io.quarkus.panache.common.deployment.HibernateMetamodelForFieldAccessBuildItem"},{"count":1,"class":"io.quarkus.deployment.dev.ExceptionNotificationBuildItem"},{"count":1,"class":"io.quarkus.panache.common.deployment.HibernateEnhancersRegisteredBuildItem"},{"count":1,"class":"io.quarkus.datasource.deployment.spi.DevServicesDatasourceResultBuildItem"},{"count":1,"class":"io.quarkus.hibernate.orm.deployment.AdditionalJpaModelBuildItem"},{"count":1,"class":"io.quarkus.arc.deployment.ValidationPhaseBuildItem"},{"count":1,"class":"io.quarkus.netty.deployment.EventLoopSupplierBuildItem"},{"count":1,"class":"io.quarkus.arc.deployment.BeanArchiveIndexBuildItem"},{"count":1,"class":"io.quarkus.undertow.deployment.ServletDeploymentManagerBuildItem"},{"count":1,"class":"io.quarkus.deployment.builditem.ConsoleFormatterBannerBuildItem"},{"count":1,"class":"io.quarkus.arc.deployment.SuppressConditionGeneratorBuildItem"},{"count":1,"class":"io.quarkus.deployment.builditem.ApplicationArchivesBuildItem"},{"count":1,"class":"io.quarkus.deployment.BooleanSupplierFactoryBuildItem"},{"count":1,"class":"io.quarkus.deployment.builditem.ContextHandlerBuildItem"},{"count":1,"class":"io.quarkus.hibernate.orm.deployment.ImpliedBlockingPersistenceUnitTypeBuildItem"},{"count":1,"class":"io.quarkus.arc.deployment.TransformedAnnotationsBuildItem"},{"count":1,"class":"io.quarkus.datasource.deployment.spi.DevServicesDatasourceProviderBuildItem"},{"count":1,"class":"io.quarkus.deployment.builditem.GeneratedFileSystemResourceHandledBuildItem"},{"count":1,"class":"io.quarkus.deployment.builditem.DevServicesLauncherConfigResultBuildItem"},{"count":1,"class":"io.quarkus.hibernate.orm.deployment.PersistenceProviderSetUpBuildItem"},{"count":1,"class":"io.quarkus.deployment.pkg.builditem.OutputTargetBuildItem"},{"count":1,"class":"io.quarkus.resteasy.deployment.ResteasyJaxrsConfigBuildItem"},{"count":1,"class":"io.quarkus.panache.common.deployment.PanacheEntityClassesBuildItem"},{"count":1,"class":"io.quarkus.resteasy.server.common.spi.ResteasyJaxrsConfigBuildItem"},{"count":1,"class":"io.quarkus.arc.deployment.PreBeanContainerBuildItem"},{"count":1,"class":"io.quarkus.arc.deployment.InjectionPointTransformerBuildItem"},{"count":1,"class":"io.quarkus.deployment.builditem.ThreadFactoryBuildItem"},{"count":1,"class":"io.quarkus.vertx.http.deployment.devmode.console.DevConsoleProcessor$HistoryHandlerBuildItem"},{"count":1,"class":"io.quarkus.deployment.builditem.ApplicationIndexBuildItem"},{"count":1,"class":"io.quarkus.panache.common.deployment.HibernateModelClassCandidatesForFieldAccessBuildItem"},{"count":1,"class":"io.quarkus.vertx.http.deployment.webjar.WebJarResultsBuildItem"},{"count":1,"class":"io.quarkus.agroal.spi.JdbcDriverBuildItem"},{"count":1,"class":"io.quarkus.hibernate.orm.deployment.JpaModelPersistenceUnitContributionBuildItem"},{"count":1,"class":"io.quarkus.undertow.deployment.ListenerBuildItem"},{"count":1,"class":"io.quarkus.undertow.deployment.FilterBuildItem"},{"count":1,"class":"io.quarkus.arc.deployment.StereotypeRegistrarBuildItem"},{"count":1,"class":"io.quarkus.vertx.http.deployment.NonApplicationRootPathBuildItem"},{"count":1,"class":"io.quarkus.vertx.http.deployment.VertxWebRouterBuildItem"},{"count":1,"class":"io.quarkus.deployment.builditem.CombinedIndexBuildItem"},{"count":1,"class":"io.quarkus.devui.deployment.JsonRPCMethodsBuildItem"},{"count":1,"class":"io.quarkus.deployment.Capabilities"},{"count":1,"class":"io.quarkus.arc.deployment.GeneratedBeanBuildItem"},{"count":1,"class":"io.quarkus.devui.deployment.ExtensionsBuildItem"},{"count":1,"class":"io.quarkus.deployment.logging.LoggingSetupBuildItem"},{"count":1,"class":"io.quarkus.deployment.builditem.ExecutorBuildItem"},{"count":1,"class":"io.quarkus.deployment.builditem.WebSocketLogHandlerBuildItem"},{"count":1,"class":"io.quarkus.resteasy.common.deployment.ResteasyInjectionReadyBuildItem"},{"count":1,"class":"io.quarkus.deployment.builditem.ExtensionSslNativeSupportBuildItem"},{"count":1,"class":"io.quarkus.smallrye.context.deployment.spi.ThreadContextProviderBuildItem"},{"count":1,"class":"io.quarkus.arc.deployment.BeanRegistrationPhaseBuildItem"},{"count":1,"class":"io.quarkus.arc.deployment.ObserverRegistrationPhaseBuildItem"},{"count":1,"class":"io.quarkus.deployment.builditem.ApplicationClassNameBuildItem"},{"count":1,"class":"io.quarkus.undertow.deployment.KnownPathsBuildItem"},{"count":1,"class":"io.quarkus.deployment.builditem.StreamingLogHandlerBuildItem"},{"count":1,"class":"io.quarkus.vertx.http.deployment.SecurityInformationBuildItem"},{"count":1,"class":"io.quarkus.deployment.dev.DisableInstrumentationForIndexPredicateBuildItem"},{"count":1,"class":"io.quarkus.resteasy.server.common.deployment.ResteasyServerConfigBuildItem"},{"count":1,"class":"io.quarkus.hibernate.orm.deployment.JpaModelBuildItem"},{"count":1,"class":"io.quarkus.vertx.deployment.VertxBuildItem"},{"count":1,"class":"io.quarkus.arc.deployment.BeanContainerBuildItem"},{"count":1,"class":"io.quarkus.arc.deployment.CurrentContextFactoryBuildItem"},{"count":1,"class":"io.quarkus.deployment.ide.EffectiveIdeBuildItem"},{"count":1,"class":"io.quarkus.undertow.deployment.ServletContextPathBuildItem"},{"count":1,"class":"io.quarkus.deployment.pkg.builditem.CurateOutcomeBuildItem"},{"count":1,"class":"io.quarkus.vertx.http.deployment.HttpRootPathBuildItem"},{"count":1,"class":"io.quarkus.deployment.builditem.ConfigurationBuildItem"},{"count":1,"class":"io.quarkus.undertow.deployment.WebMetadataBuildItem"},{"count":1,"class":"io.quarkus.deployment.steps.CapabilityAggregationStep$CapabilitiesConfiguredInDescriptorsBuildItem"},{"count":1,"class":"io.quarkus.deployment.builditem.ApplicationStartBuildItem"},{"count":1,"class":"io.quarkus.deployment.builditem.ApplicationClassPredicateBuildItem"},{"count":1,"class":"io.quarkus.agroal.deployment.AggregatedDataSourceBuildTimeConfigBuildItem"},{"count":1,"class":"io.quarkus.vertx.http.deployment.BodyHandlerBuildItem"},{"count":1,"class":"io.quarkus.deployment.builditem.LogCategoryMinLevelDefaultsBuildItem"},{"count":1,"class":"io.quarkus.deployment.builditem.GeneratedResourceBuildItem"},{"count":1,"class":"io.quarkus.arc.deployment.ContextRegistrationPhaseBuildItem"},{"count":1,"class":"io.quarkus.deployment.builditem.IOThreadDetectorBuildItem"},{"count":1,"class":"io.quarkus.arc.deployment.CustomScopeAnnotationsBuildItem"},{"count":1,"class":"io.quarkus.deployment.builditem.SslNativeConfigBuildItem"},{"count":1,"class":"io.quarkus.hibernate.orm.deployment.PersistenceUnitDescriptorBuildItem"},{"count":1,"class":"io.quarkus.resteasy.server.common.deployment.ResteasyDeploymentBuildItem"},{"count":1,"class":"io.quarkus.arc.deployment.AutoInjectAnnotationBuildItem"},{"count":1,"class":"io.quarkus.arc.deployment.CompletedApplicationClassPredicateBuildItem"},{"count":1,"class":"io.quarkus.agroal.spi.JdbcDataSourceBuildItem"},{"count":1,"class":"io.quarkus.deployment.builditem.ApplicationInfoBuildItem"},{"count":1,"class":"io.quarkus.deployment.builditem.StaticInitConfigSourceFactoryBuildItem"},{"count":1,"class":"io.quarkus.deployment.ide.IdeRunningProcessBuildItem"},{"count":1,"class":"io.quarkus.arc.deployment.BeanContainerListenerBuildItem"},{"count":1,"class":"io.quarkus.deployment.ide.IdeFileBuildItem"},{"count":1,"class":"io.quarkus.deployment.builditem.MainClassBuildItem"}],"itemsCount":1945,"buildTarget":"ohmydog-backend-1.0.0-SNAPSHOT"}